{"version":"1.0.2","api":{"Prod":{"type":"data","read_level":0,"write_level":0,"attributes":{"profile":{"type":"int","value":1},"cycle":{"type":"int","value":1},"day":{"type":"int","value":1},"cmd":{"type":"string","value":"Start","size":10}}},"DO":{"type":"data","read_level":0,"write_level":0,"attributes":{"sampletime":{"type":"int","value":10},"nighonly":{"type":"bool","value":false},"docontrol":{"type":"bool","value":false},"KD":{"type":"double","value":1.5},"KI":{"type":"double","value":0.05},"KP":{"type":"double","value":1.1},"setpoint":{"type":"double","value":5.1}}},"modbInverter":{"type":"data","read_level":0,"write_level":0,"attributes":{"refresh_rate":{"type":"int","value":10,"size":null},"InverterAddress":{"type":"int","value":1},"I10_LoadUsedHoyMux":{"type":"double","value":10},"I10_LoadUsedHoyType":{"type":"int","value":1},"I10_LoadUsedHoyPoints":{"type":"int","value":2},"I10_LoadUsedHoyStart":{"type":"int","value":61530},"I10_LoadUsedHoyOff":{"type":"int","value":0},"I9_BatDscHoyMux":{"type":"double","value":10,"format":""},"I9_BatDscHoyType":{"type":"int","value":1},"I9_BatDscHoyPoints":{"type":"int","value":1},"I9_BatDscHoyStart":{"type":"int","value":61518},"I9_BatDscHoyOff":{"type":"int","value":0},"I8_BatChdHoyMux":{"type":"double","value":10},"I8_BatChdHoyType":{"type":"int","value":1},"I8_BatChdHoyPoints":{"type":"int","value":1},"I8_BatChdHoyStart":{"type":"int","value":61517},"I8_BatChdHoyOff":{"type":"int","value":0},"I7_LoadUsedTotalMux":{"type":"double","value":10},"I7_LoadUsedTotalType":{"type":"int","value":1},"I7_LoadUsedTotalPoints":{"type":"int","value":2},"I7_LoadUsedTotalStart":{"type":"int","value":61528,"comment":" "},"I7_LoadUsedTotalOff":{"type":"int","value":0},"I6_UsedkwhHoyMux":{"type":"double","value":10},"I6_UsedkwhHoyType":{"type":"int","value":1},"I6_UsedkwhHoyPoints":{"type":"int","value":1},"I6_UsedkwhHoyStart":{"type":"int","value":61526},"I6_UsedkwhHoyOff":{"type":"int","value":0},"I5_GenkWhHoyMux":{"type":"double","value":10},"I5_GenkWhHoyType":{"type":"int","value":1},"I5_GenkWhHoyPoints":{"type":"int","value":1},"I5_GenkWhHoyStart":{"type":"int","value":61527},"I5_GenkWhHoyOff":{"type":"int","value":0},"I4_BatDscTotalMux":{"type":"double","value":10},"I4_BatDscTotalType":{"type":"int","value":1},"I4_BatDscTotalPoints":{"type":"int","value":2},"I4_BatDscTotalStart":{"type":"int","value":61522},"I4_BatDscTotalOff":{"type":"int","value":0},"I3_BatChgTotalMux":{"type":"double","value":10},"I3_BatChgTotalType":{"type":"int","value":1},"I3_BatChgTotalPoints":{"type":"int","value":2},"I3_BatChgTotalStart":{"type":"int","value":61520},"I3_BatChgTotalOff":{"type":"int","value":0},"I2_BatDscHoyMux":{"type":"double","value":10},"I2_BatDscHoyType":{"type":"int","value":1},"I2_BatDscHoyPoints":{"type":"int","value":1},"I2_BatDscHoyStart":{"type":"int","value":61518},"I2_BatDscHoyOff":{"type":"int","value":0},"I1_BatChHoyMux":{"type":"double","value":10},"I1_BatChHoyType":{"type":"int","value":1},"I1_BatChHoyPoints":{"type":"int","value":1},"I1_BatChHoyStart":{"type":"int","value":61517},"I1_BatChHoyOff":{"type":"int","value":0}}},"modbSensors":{"type":"data","read_level":0,"write_level":0,"attributes":{"refresh_rate":{"type":"int","value":15},"level":{"type":"int","value":42},"humMux":{"type":"double","value":1.5,"format":"%.02f"},"humType":{"type":"int","value":1},"humPoints":{"type":"int","value":0},"humStart":{"type":"int","value":0},"HumOffset":{"type":"int","value":-1},"HAddress":{"type":"int","value":20},"AMux":{"type":"double","value":1},"AType":{"type":"int","value":1},"APoints":{"type":"int","value":0},"AStart":{"type":"int","value":0},"AOffset":{"type":"int","value":-1},"AAddress":{"type":"int","value":19},"PHMux":{"type":"double","value":1},"PHType":{"type":"int","value":1},"PHPoints":{"type":"int","value":0},"PHStart":{"type":"int","value":0},"PHOffset":{"type":"int","value":-1},"PHAddress":{"type":"int","value":17},"DOMux":{"type":"double","value":1},"DOType":{"type":"int","value":1},"DOPoints":{"type":"int","value":6},"DOStart":{"type":"int","value":8192},"DOOffset":{"type":"int","value":0},"DOAddress":{"type":"int","value":16},"WMux":{"type":"double","value":1},"WType":{"type":"int","value":1},"WPoints":{"type":"int","value":2},"WStart":{"type":"int","value":8192},"WOffset":{"type":"int","value":0},"WAddress":{"type":"int","value":16}}},"modbBattery":{"type":"data","read_level":0,"write_level":0,"attributes":{"refresh_rate":{"type":"int","value":30},"batAddress":{"type":"int","value":3},"tempMux":{"type":"double","value":10},"tempType":{"type":"int","value":1},"tempPoints":{"type":"int","value":1},"tempStart":{"type":"int","value":276},"tempOffset":{"type":"int","value":0},"cycleMux":{"type":"double","value":1},"cycleType":{"type":"int","value":1},"cyclePoints":{"type":"int","value":1},"cycleStart":{"type":"int","value":268},"cycleOffset":{"type":"int","value":0},"SOHMux":{"type":"double","value":1},"SOHType":{"type":"int","value":1},"SOHPoints":{"type":"int","value":1},"SOHStart":{"type":"int","value":260},"SOHOffset":{"type":"int","value":0},"SOCMux":{"type":"double","value":1},"SOCType":{"type":"int","value":1},"SOCPoints":{"type":"int","value":1},"SOCStart":{"type":"int","value":256},"SOCOffset":{"type":"int","value":0}}},"modbPanels":{"type":"data","read_level":0,"write_level":0,"attributes":{"refresh_rate":{"type":"int","value":30},"PVAddress":{"type":"int","value":4},"PV2AmpsMux":{"type":"double","value":10,"format":""},"PV2AmpsType":{"type":"int","value":1},"PV2AmpsPoints":{"type":"int","value":1},"PV2AmpsStart":{"type":"int","value":272},"PV2AmpsOffset":{"type":"int","value":0},"PV2VMux":{"type":"double","value":10},"PV2VoltsType":{"type":"int","value":1},"PV2VPoints":{"type":"int","value":1},"PV2VStart":{"type":"int","value":271},"PV2VoltsOffset":{"type":"int","value":0},"PV1AmpsMux":{"type":"double","value":10},"PV1AmpsType":{"type":"int","value":1},"PV1AmpsPoints":{"type":"int","value":1},"PV1AmpsStart":{"type":"int","value":264},"PV1_AmpsOffset":{"type":"int","value":0},"PV1VMux":{"type":"double","value":10},"PV1VType":{"type":"int","value":1},"PV1VPoints":{"type":"int","value":1},"PV1VStart":{"type":"int","value":263},"PV1VoltsOffset":{"type":"int","value":0},"ChargeMux":{"type":"double","value":1},"ChargeType":{"type":"int","value":1},"ChargePoints":{"type":"int","value":1},"ChargeStart":{"type":"int","value":267},"Charge_StateOffset":{"type":"int","value":0}}},"reboot":{"type":"action","read_level":0,"write_level":0},"limits":{"type":"data","read_level":0,"write_level":0,"attributes":{"hummax":{"type":"int","value":90},"hummin":{"type":"int","value":50},"atempmax":{"type":"int","value":32},"atempmin":{"type":"int","value":19},"wtempmax":{"type":"int","value":31},"wtempmin":{"type":"int","value":19},"phmax":{"type":"int","value":70},"phmin":{"type":"int","value":50},"domax":{"type":"int","value":70},"domin":{"type":"int","value":40},"kwchoymax":{"type":"int","value":42},"kwchoymin":{"type":"int","value":40},"kwbatdhoymax":{"type":"int","value":42},"kwbatdhoymin":{"type":"int","value":40},"kwbatchoymax":{"type":"int","value":42},"kwbatchoymin":{"type":"int","value":40},"kwloadhoymax":{"type":"int","value":42},"kwloadhoymin":{"type":"int","value":40},"kwctodaymax":{"type":"int","value":42},"kwctodaymin":{"type":"int","value":40},"kwgtodaymax":{"type":"int","value":42},"kwgtodaymin":{"type":"int","value":40},"bdATotmax":{"type":"int","value":820},"bdATotmin":{"type":"int","value":720},"bcATotmax":{"type":"int","value":850},"bcATotmin":{"type":"int","value":720},"bdAhoymax":{"type":"int","value":820},"bdAhoymin":{"type":"int","value":720},"bcAhoymax":{"type":"int","value":820},"bcAhoymin":{"type":"int","value":780},"btempmax":{"type":"int","value":50},"btempmin":{"type":"int","value":10},"bcyclemax":{"type":"int","value":5000},"bcyclemin":{"type":"int","value":0},"bSOHmax":{"type":"int","value":100},"bSOHmin":{"type":"int","value":20},"bSOCmax":{"type":"int","value":80},"bSOCmin":{"type":"int","value":20},"amax":{"type":"int","value":15},"amin":{"type":"int","value":14},"vmax":{"type":"int","value":390},"vmin":{"type":"int","value":340}}},"profile":{"type":"data","read_level":0,"write_level":0,"attributes":{"msg":{"type":"string","value":"","size":30},"schedule":{"type":"string","value":"","size":10000}}},"settings":{"type":"data","read_level":0,"write_level":0,"attributes":{"meshwifi_val":{"type":"bool","value":false},"wifi_val":{"type":"bool","value":false},"delay_val":{"type":"bool","value":false},"nodes_val":{"type":"int","value":0},"unit_val":{"type":"int","value":0},"disable_val":{"type":"int","value":0},"msg_val":{"type":"string","value":"","size":60},"challenge_val":{"type":"string","value":"","size":16},"master_val":{"type":"bool","value":false},"pool_val":{"type":"int","value":0},"mac_val":{"type":"string","value":"","size":10}},"readonly":false},"system":{"type":"data","read_level":0,"write_level":0,"attributes":{"mqttreco_val":{"type":"int","value":1000},"otf_val":{"type":"bool","value":false},"version_val":{"type":"string","value":"5.0.1","size":20},"skipopt_val":{"type":"bool","value":false},"skip_val":{"type":"int","value":3},"repeat_val":{"type":"int","value":5},"baset_val":{"type":"int","value":25},"maxamp_val":{"type":"int","value":0},"minamp_val":{"type":"int","value":0},"password_val":{"type":"string","value":"","size":16},"loglevel_val":{"type":"string","value":"","size":10},"mqttpass_val":{"type":"string","value":"csttpstt","size":30},"mqttuser_val":{"type":"string","value":"robert","size":30},"mqttserver_val":{"type":"string","value":"http://64.123.180.233:1883","size":60},"mqttcert_val":{"type":"string","value":"","size":1900},"logtime_val":{"type":"int","value":60000,"size":100},"ssidpass_val":{"type":"string","value":"","size":16},"ssid_val":{"type":"string","value":"","size":30},"meshid_val":{"type":"int","value":0},"security_val":{"type":"bool","value":false},"nodes_val":{"type":"int","value":400000},"conns_val":{"type":"int","value":10000}},"readonly":false},"sysset":{"type":"data","read_level":0,"write_level":0,"attributes":{"idf_val":{"type":"string","value":"","size":100},"compile_val":{"type":"string","value":"","size":100},"boot_val":{"type":"int","value":0},"lreason_val":{"type":"int","value":0},"security_val":{"type":"bool","value":false},"display_val":{"type":"bool","value":false},"writes_val":{"type":"int","value":0},"reads_val":{"type":"int","value":0},"nodetype_val":{"type":"string","value":"","size":10},"mac_val":{"type":"string","value":"","size":20},"mesh_val":{"type":"string","value":"","size":20},"bytesin_val":{"type":"int","value":0},"bytesout_val":{"type":"int","value":0},"msgin_val":{"type":"int","value":0},"msgout_val":{"type":"int","value":0},"conns_val":{"type":"int","value":0},"disco_val":{"type":"int","value":0},"ldate_val":{"type":"string","value":"","size":100}}}},"ui":{"production":false,"brand":"Brand Name","logo":"<?xml version=\"1.0\" standalone=\"no\"?>\n<!DOCTYPE svg PUBLIC \"-//W3C//DTD SVG 20010904//EN\"\n \"http://www.w3.org/TR/2001/REC-SVG-20010904/DTD/svg10.dtd\">\n<svg version=\"1.0\" xmlns=\"http://www.w3.org/2000/svg\"\n width=\"288.000000pt\" height=\"100.000000pt\" viewBox=\"0 0 288.000000 100.000000\"\n preserveAspectRatio=\"xMidYMid meet\">\n\n<g transform=\"translate(0.000000,100.000000) scale(0.100000,-0.100000)\"\nfill=\"#000000\" stroke=\"none\">\n<path d=\"M2435 816 c-42 -13 -85 -63 -85 -98 0 -53 48 -102 122 -124 101 -31\n136 -85 84 -133 -21 -20 -32 -22 -88 -18 -34 3 -78 8 -95 12 -26 6 -33 4 -33\n-7 0 -43 109 -73 197 -56 83 17 119 65 106 145 -7 44 -39 70 -124 101 -90 34\n-114 63 -85 107 l18 28 94 -6 c52 -3 94 -2 94 2 0 14 -34 38 -69 50 -42 14\n-84 13 -136 -3z\"/>\n<path d=\"M861 806 c-8 -9 -11 -73 -9 -207 l3 -194 27 -3 c23 -3 28 1 33 30 3\n18 5 86 3 151 -4 155 10 153 75 -8 52 -130 55 -137 62 -160 3 -9 17 -15 35\n-15 26 0 33 6 52 48 11 26 24 56 28 67 5 11 14 36 22 55 8 19 21 51 28 70 18\n46 41 82 48 75 4 -3 6 -74 7 -158 l0 -152 30 0 30 0 3 194 c2 134 -1 198 -9\n207 -28 34 -119 2 -119 -41 0 -8 -4 -23 -9 -33 -12 -22 -32 -70 -66 -159 -30\n-78 -49 -91 -65 -45 -6 15 -14 36 -19 47 -5 11 -26 65 -47 120 -20 55 -44 106\n-52 113 -21 16 -77 15 -91 -2z\"/>\n<path d=\"M1517 813 c-4 -3 -7 -98 -7 -210 l0 -203 136 0 c124 0 135 2 132 18\n-3 14 -17 17 -93 20 -70 2 -93 6 -102 19 -16 21 -17 105 -1 121 7 7 36 12 66\n12 59 0 92 13 92 35 0 12 -16 15 -73 15 -82 0 -97 9 -97 54 0 74 3 76 100 76\n64 0 91 4 100 15 6 8 9 19 5 25 -7 11 -247 15 -258 3z\"/>\n<path d=\"M1938 814 c-5 -4 -8 -99 -8 -211 l0 -203 30 0 29 0 3 78 3 77 70 5\nc39 3 85 13 102 23 83 44 83 163 1 212 -32 18 -216 34 -230 19z m175 -56 c48\n-25 60 -69 31 -113 -11 -17 -32 -28 -69 -36 -75 -17 -85 -7 -85 81 0 36 3 70\n7 73 11 11 93 8 116 -5z\"/>\n<path d=\"M2806 805 c-13 -14 -16 -43 -16 -188 0 -206 2 -217 41 -217 l29 0 -2\n207 c-3 183 -5 208 -19 211 -9 2 -24 -4 -33 -13z\"/>\n<path d=\"M29 251 c-13 -69 64 -178 154 -218 20 -9 37 -20 37 -25 0 -4 43 -8\n95 -8 52 0 95 4 95 9 0 5 10 13 23 17 73 23 162 124 174 198 5 35 4 36 -24 36\n-25 0 -33 -7 -51 -42 -28 -55 -39 -68 -82 -99 -103 -75 -263 -45 -336 63 -16\n24 -32 49 -35 57 -5 14 -48 24 -50 12z\"/>\n</g>\n</svg>\n","toolbar":{"css":"flex-grow: 1;","layout":[{"classes":"container","css":"flex-grow: 1;\njustify-content: center;","layout":[{"classes":"container","css":"align-items: center;","layout":[{"type":"image","image":"<?xml version=\"1.0\" encoding=\"utf-8\"?>\n<svg viewBox=\"0 0 600 150\" xmlns=\"http://www.w3.org/2000/svg\">\n  <rect x=\"0\" y=\"0\" width=\"600\" height=\"150\" rx=\"20\" ry=\"20\" style=\"stroke: none; fill: #e1e5e9;\"/>\n  <text style=\"fill: #94A3B8; font-family: Arial, sans-serif; font-size: 92px;dominant-baseline: middle; text-anchor: middle; \" x=\"50%\" y=\"50%\">my logo</text>\n</svg>","css":"width: 8.5rem; height: 1.5rem; align-items: center; justify-content: center; display: flex;"}]},{"classes":"container","css":"margin-left: auto; align-items: center","layout":[{"type":"text","format":"My product console"}]}]}]},"theme":{"buttonBgColor":"#65abc3","buttonBorderColor":"#65abc3","buttonHoverColor":"#65abc3"},"pages":[{"title":"Controller Unit","icon":"settings","classes":"page","layout":[{"classes":"container","css":"flex: 0 0 auto;\nheight: 14.8515625rem;\nwidth: 27.25rem;\ngap: 0.5rem;\nflex-wrap: wrap;","layout":[{"classes":"panel","css":"flex: 0 0 auto;\nheight: 14.8515625rem;\nbackground: #ffffff;\nflex-basis: 0 0 auto;\nwidth: 27.25rem;","layout":[{"classes":"container","css":"height: 3.25rem;\ncolor: #fefbfb;\nbackground: #86a3ac;\njustify-content: center;\ngap: 0.5rem;","layout":[{"classes":"title","format":"Controller","css":"font-size: 2rem;\nheight: 2.3876953125rem;"}]},{"classes":"labeled","layout":[{"classes":"label","format":"Challenge","css":"flex: 0 0 auto;\nheight: 1.0625rem;\nwidth: 3.25390625rem;"},{"type":"input","ref":"settings.mac_val","css":"flex: 0 0 auto;\nwidth: 8rem;\ntext-align: center;","input":"text","autosave":false,"disabled":"${settings.disable_val==1}"},{"format":"Key"},{"type":"input","ref":"settings.challenge_val","css":"flex: 0 0 auto;\nheight: 1.5625rem;\nwidth: 10.1875rem;","input":"password","disabled":"${settings.disable_val==1}"}],"css":"justify-content: center;"},{"classes":"labeled","layout":[{"classes":"label","format":"Pool","css":"flex: 0 0 auto;\nheight: 1.0625rem;\nwidth: 1.7607421875rem;"},{"type":"input","ref":"settings.pool_val","css":"flex: 0 0 auto;\nwidth: 3rem;\ntext-align: center;","input":"number","autosave":false,"disabled":"${settings.disable_val==1}"},{"format":"Unit","css":"flex: 0 0 auto;\nheight: 1.0625rem;\nwidth: 1.65234375rem;"},{"type":"input","ref":"settings.unit_val","css":"flex: 0 0 auto;\nwidth: 3rem;\ntext-align: center;","input":"number","autosave":false,"disabled":"${settings.disable_val==1}"},{"format":"Nodes","css":"flex: 0 0 auto;\nheight: 1.0625rem;\nwidth: 1.65234375rem;"},{"type":"input","ref":"settings.nodes_val","css":"flex: 0 0 auto;\nwidth: 3rem;\ntext-align: center;","input":"number","autosave":false}],"css":"justify-content: center;"},{"classes":"labeled","layout":[{"classes":"label","format":"Mesh","css":"flex: 0 0 auto;\nwidth: 2.5rem;\nheight: 1.0625rem;"},{"type":"toggle","ref":"settings.wifi_val","css":"flex: 0 0 auto;\nwidth: 84rem;\nheight: 1.5rem;"},{"classes":"label","format":"Root","css":"flex: 0 0 auto;\nwidth: 2.25rem;\nheight: 1.25rem;"},{"type":"toggle","ref":"settings.master_val","css":"flex: 0 0 auto;\nwidth: 4rem;\nheight: 1.599609375rem;"},{"classes":"label","format":"WMesh","css":"flex: 0 0 auto;\nwidth: 2.25rem;\nheight: 1.25rem;"},{"type":"toggle","ref":"settings.meshwifi_val","css":"flex: 0 0 auto;\nwidth: 4rem;\nheight: 1.599609375rem;"},{"classes":"label","format":"Dly","css":"flex: 0 0 auto;\nwidth: 1.5rem;\nheight: 1.25rem;"},{"type":"toggle","ref":"settings.delay_val","css":"flex: 0 0 auto;\nwidth: 4rem;\nheight: 1.599609375rem;"}]},{"classes":"labeled","layout":[{"type":"savebutton","title":"Save & Reboot","icon":"save","ref":"settings","css":"flex: 0 0 auto;\nwidth: 25.921875rem;\nfont-size: 1.25rem;\nheight: 2.001953125rem;","disabled":"${settings.disable_val>0}"}]},{"classes":"labeled","layout":[{"type":"input","ref":"settings.msg_val","input":"text","disabled":"${true}","css":"flex: 0 0 auto;\nflex-grow: 1;\ncolor: #86a3ac;\nfont-weight: 800;\nwidth: 25.75rem;\ntext-align: center;\nheight: 1.75rem;\nfont-size: 2rem;"}],"css":"flex: 0 0 auto;\nheight: 1.75rem;\nwidth: 20rem;"}]}]}],"css":"flex: 0 0 auto;\nwidth: 15.75rem;\nheight: 1.6416015625rem;"},{"title":"Configure System","icon":"desktop","classes":"page","layout":[{"classes":"container","css":"flex: 0 0 auto;\nheight: 2.75rem;\nwidth: 46rem;\njustify-content: center;\nbackground: #86a3ac;\ngap: 0.5rem;\nflex-wrap: wrap;","layout":[{"format":"ShrimpIoT","css":"flex: 0 0 auto;\nwidth: 8.6552734375rem;\ncolor: #fafafa;\nfont-size: 2rem;\nheight: 2.375rem;"},{"format":"${system.version_val}","css":"font-weight: 500;\nfont-size: 2rem;","error":true}]},{"classes":"container","css":"flex: 0 0 auto;\nheight: 34.451171875rem;\nwidth: 46.75rem;\ngap: 0.5rem;\nflex-wrap: wrap;","layout":[{"classes":"panel","css":"flex-basis: 0 0 auto;","layout":[{"classes":"container","css":"flex: 0 0 auto;\nbackground: #86a3ac;\nheight: 3.2373046875rem;\nwidth: 20.5rem;\ngap: 0.5rem;","layout":[{"classes":"title","format":"Network Stuff","css":"flex: 0 0 auto;\nwidth: 19rem;\nfont-size: 2rem;\nheight: 2.375rem;\ntext-align: center;"}]},{"classes":"labeled","layout":[{"classes":"label","format":"MESH","css":"font-weight: 100;\nfont-size: 1.5rem;"},{"type":"input","ref":"system.meshid_val","css":"flex: 0 0 auto;\nwidth: 8.25rem;\nfont-size: 1.5rem;\ntext-align: center;","input":"number","disabled":"${settings.disable_val==1}"}]},{"classes":"labeled","layout":[{"classes":"label","format":"SSID","css":"margin-top: 0.75rem;\nfont-weight: 100;\nfont-size: 1.5rem;\nheight: 1.0625rem;"},{"type":"input","ref":"system.ssid_val","css":"font-size: 1.2rem;\nmargin-top: 0.5rem;"}],"css":"align-items: start;"},{"classes":"labeled","layout":[{"classes":"label","format":"Pswd","css":"flex: 0 0 auto;\nfont-weight: 100;\nfont-size: 1.5rem;\nwidth: 3.5439453125rem;\nheight: 2.5rem;"},{"type":"input","ref":"system.ssidpass_val","css":"font-size: 1.2rem;"}],"css":"align-items: center;"},{"classes":"labeled","layout":[{"classes":"label","format":"Log Time","css":"flex: 0 0 auto;\nfont-weight: 100;\nfont-size: 1.5rem;\nwidth: 6.5rem;\nheight: 2.5rem;"},{"type":"input","ref":"system.logtime_val","css":"flex: 0 0 auto;\nheight: 1.9375rem;\nwidth: 6.75rem;\nfont-size: 1.1rem;","input":"number"}],"css":"align-items: start;"}]},{"classes":"panel","css":"flex: 0 0 auto;\nheight: 17.5rem;\nwidth: 25rem;\nflex-basis: 0 0 auto;","layout":[{"classes":"container","css":"background: #86a3ac;\nflex: 0 0 auto;\nheight: 3.25rem;\nwidth: 24.75rem;\ngap: 0.5rem;","layout":[{"classes":"title","format":"Mqtt Stuff","css":"flex: 0 0 auto;\nheight: 2.35rem;\nfont-size: 2rem;\ntext-align: center;\nwidth: 23.25rem;\ngap: 0.5rem;"}]},{"classes":"labeled","layout":[{"classes":"label","format":"Server","css":"flex: 0 0 auto;\nfont-weight: 100;\nfont-size: 2rem;\nheight: 2.5rem;\nwidth: 4.7744140625rem;"},{"type":"input","ref":"system.mqttserver_val","css":"flex: 0 0 auto;\nfont-size: 1.1rem;\nwidth: 15.75rem;"}],"css":"flex: 0 0 auto;\nwidth: 23rem;\nheight: 2.5rem;"},{"classes":"labeled","layout":[{"classes":"label","format":"User","css":"flex: 0 0 auto;\nfont-weight: 100;\nfont-size: 2rem;\nheight: 1.0625rem;\nwidth: 4.7744140625rem;"},{"type":"input","ref":"system.mqttuser_val","css":"flex: 0 0 auto;\nfont-size: 1.2rem;\nheight: 1.5625rem;\nwidth: 15.75rem;\nmargin-top: 0.75rem;"}],"css":"flex: 0 0 auto;\nwidth: 23rem;\nheight: 2.5rem;\nalign-items: start;"},{"classes":"labeled","layout":[{"classes":"label","format":"Pswd","css":"flex: 0 0 auto;\nfont-weight: 100;\nfont-size: 2rem;\nheight: 2.375rem;\nwidth: 4.7744140625rem;"},{"type":"input","ref":"system.mqttpass_val","css":"font-size: 1.2rem;\nflex: 0 0 auto;\nwidth: 15.75rem;\nmargin-top: 0.75rem;"}],"css":"flex: 0 0 auto;\nwidth: 23rem;\nheight: 2.5rem;\nalign-items: start;"},{"classes":"labeled","layout":[{"classes":"label","format":"CertF","css":"margin-top: 1.5rem;\nflex: 0 0 auto;\nfont-weight: 100;\nfont-size: 2rem;\nheight: 2.375rem;\nwidth: 4.7744140625rem;"},{"type":"input","ref":"system.mqttcert_val","css":"flex: 0 0 auto;\nheight: 3.75rem;\nwidth: 15.75rem;\nmargin-top: 0.75rem;"}],"css":"flex: 0 0 auto;\nwidth: 23rem;\nheight: 2.5rem;\nalign-items: start;"}]},{"classes":"panel","css":"flex: 0 0 auto;\nheight: 16.75rem;\nwidth: 20.5rem;\nflex-basis: 0 0 auto;","layout":[{"classes":"container","css":"flex: 0 0 auto;\nbackground: #86a3ac;\njustify-content: center;\nheight: 3.25rem;\nwidth: 20.5rem;\ngap: 0.5rem;","layout":[{"classes":"title","format":"Pool","css":"font-size: 2rem;\nheight: 2.3876953125rem;"}]},{"classes":"container","css":"justify-content: center;\ngap: 0.5rem;\nflex-wrap: wrap;","layout":[{"format":"Nodes","css":"padding-right: 0.5rem;\nheight: 2.375rem;\nfont-weight: 100;\nfont-size: 2rem;"},{"type":"input","ref":"system.nodes_val","input":"number","css":"flex: 0 0 auto;\ntext-align: center;\nfont-size: 1.5rem;\nheight: 2rem;\nwidth: 8.75rem;","disabled":"${settings.disable_val==1}\n"}]},{"classes":"container","css":"justify-content: center;\ngap: 0.5rem;\nflex-wrap: wrap;","layout":[{"format":"","css":"padding-right: 0.5rem;\nheight: 2.375rem;\nfont-weight: 100;\nfont-size: 2rem;"},{"type":"input","ref":"system.conns_val","input":"number","css":"flex: 0 0 auto;\ntext-align: center;\nfont-size: 1.5rem;\nheight: 2rem;\nwidth: 8.75rem;","disabled":"\n${settings.disable_val==1}"},{"classes":"label","format":"____________Others_____________","css":"margin-bottom: 1rem;\nfont-size: 1rem;\nheight: 0.25rem;"}]},{"classes":"container","css":"padding-top: 1.25rem;\nalign-items: center;\ngap: 0.5rem;\nflex-wrap: wrap;","layout":[{"format":"MqttReconnect","css":"flex: 0 0 auto;\nwidth: 8.5rem;\npadding-right: 0.5rem;\nheight: 1.75rem;\nfont-weight: 100;\nfont-size: 1.2rem;"},{"type":"input","ref":"system.mqttreco_val","input":"number","css":"flex: 0 0 auto;\nmargin-left: 3rem;\ntext-align: center;\nfont-size: 1.2rem;\nheight: 2rem;\nwidth: 6rem;","disabled":"\n","min":"100","max":"10000","step":"10","tooltip":"MQTT reconnect delay"}]}]},{"classes":"panel","css":"flex: 0 0 auto;\nheight: 16.75rem;\nwidth: 25rem;\nflex-basis: 0 0 auto;","layout":[{"classes":"container","css":"background: #86a3ac;\nheight: 3.25rem;\njustify-content: center;\ngap: 0.5rem;","layout":[{"format":"Advanced System","css":"font-weight: 800;\nfont-size: 1.5rem;"}]},{"classes":"container","css":"height: 1.599609375rem;\njustify-content: center;\ngap: 0.5rem;\nflex-wrap: wrap;","layout":[{"format":"Console Pswd","css":"font-size: 1.5rem;"},{"type":"input","ref":"system.password_val","css":"margin-left: 1.5rem;\ntext-align: center;","input":"password"}]},{"classes":"labeled","layout":[{"classes":"label","format":"LogLevel","css":"flex: 0 0 auto;\nfont-size: 1.5rem;\nheight: 1rem;\nwidth: 9.75rem;"},{"type":"dropdown","ref":"system.loglevel_val","options":"None,Error,Warn,Info,Debug,Verbose","css":"margin-top: 0.75rem;\nfont-size: 1rem;"}],"css":"margin-top: 0.25rem;\nheight: 1.75rem;\nalign-items: center;\njustify-content: center;"},{"classes":"labeled","layout":[{"classes":"label","format":"BaseT","css":"height: 1.0625rem;"},{"type":"input","ref":"system.baset_val","css":"flex: 0 0 auto;\nwidth: 3.5rem;\ntext-align: center;","input":"number"},{"classes":"label","format":"RepeatT","css":"height: 1.0625rem;"},{"type":"input","ref":"system.repeat_val","css":"flex: 0 0 auto;\nwidth: 3.25rem;\ntext-align: center;","input":"number"}],"css":"margin-top: 1rem;"},{"classes":"container","css":"gap: 0.5rem;\nflex-wrap: wrap;"},{"classes":"container","css":"padding-tosavep: 0.5rem;\njustify-content: center;\nalign-items: center;\ngap: 0.5rem;\nflex-wrap: wrap;","layout":[{"type":"savebutton","title":"save","icon":"save","ref":"system","css":"flex: 0 0 auto;\nheight: 2.314453125rem;\nwidth: 23.375rem;\nfont-size: 1.5rem;"}]}]}]},{"type":"action","title":"reboot","icon":"refresh","ref":"reboot","css":"flex: 0 0 auto;\nfont-size: 1.5rem;\nheight: 1.564453125rem;\nwidth: 46rem;","disabled":"${settings.disable_val>0}"}],"css":"flex: 0 0 auto;\nwidth: 48.25rem;\nheight: 41.265625rem;"},{"title":"System Settings","icon":"archive","classes":"page","layout":[{"classes":"container","css":"gap: 0.5rem;\nflex-wrap: wrap;","layout":[{"classes":"panel","css":"flex: 0 0 auto;\nflex-basis: 0 0 auto;\nwidth: 18rem;","layout":[{"classes":"container","css":"justify-content: center;\nfont-size: 2rem;\ncolor: #FFFFFF;\nbackground: #86a3ac;\ngap: 0.5rem;","layout":[{"css":"white-space: nowrap;\ntext-overflow: ellipsis;\nfont-weight: 700;","format":"General "}]},{"css":"height: 2rem;\ndisplay: flex;\nalign-items: center;\njustify-content: center;\ngap: 1rem;","layout":[{"format":"IDF","css":"font-size: 1.5rem;\nfont-weight: 100;\nheight: 1.0625rem;"},{"format":"${sysset.idf_val}","css":"font-size: 2rem;\ntext-align: center;","error":true}]},{"css":"height: 2rem;\ndisplay: flex;\nalign-items: center;\njustify-content: space-between;\ngap: 1rem;","layout":[{"format":"Compiler","css":"font-size: 1.5rem;\nfont-weight: 100;\nheight: 1.0625rem;"},{"format":"${sysset.compile_val}","css":"flex: 0 0 auto;\ntext-align: center;\ntext-overflow: ellipsis;\nheight: 1rem;\noverflow: hidden;\nwidth: 10.75rem;\nmargin-top: 0.5rem;\nfont-weight: 300;\nfont-size: 1rem;","error":true}]},{"css":"justify-content: space-between;\nheight: 2rem;\ndisplay: flex;\ngap: 1rem;","layout":[{"format":"Boots","css":"font-size: 1.5rem;\nfont-weight: 100;\nheight: 1.0625rem;"},{"format":"${sysset.boot_val}","css":"font-weight: 500;\nmargin-top: 0.25rem;\nfont-size: 1.2rem;","error":true},{"format":"Reset","css":"font-size: 1.5rem;\nfont-weight: 100;\nheight: 1.0625rem;"},{"format":"${sysset.lreason_val}","css":"font-weight: 500;\nmargin-top: 0.25rem;\nfont-size: 1.2rem;","error":true}]},{"css":"height: 2rem;\ndisplay: flex;\nalign-items: center;\njustify-content: space-between;\ngap: 1rem;","layout":[{"format":"Security","css":"font-weight: 100;"},{"type":"toggle","ref":"sysset.security_val"},{"format":"Display","css":"font-weight: 100;"},{"type":"toggle","ref":"sysset.display_val"}]}]},{"classes":"panel","css":"flex: 0 0 auto;\nflex-basis: 0 0 auto;\nwidth: 18rem;","layout":[{"classes":"container","css":"height: 3rem;\njustify-content: center;\nfont-size: 2rem;\ncolor: #ffffff;\nbackground: #86a3ac;\ngap: 0.5rem;","layout":[{"css":"white-space: nowrap;\ntext-overflow: ellipsis;\nfont-weight: 700;","format":"FRAM"}]},{"css":"flex: 0 0 auto;\nwidth: 16.375rem;\nheight: 3rem;\nfont-weight: 1.5;\ndisplay: flex;\nalign-items: center;\njustify-content: space-between;\ngap: 1rem;","layout":[{"format":"Writes","css":"flex: 0 0 auto;\nfont-weight: 100;\nfont-size: 1.5rem;\nheight: 1.0625rem;\nwidth: 5rem;"},{"format":"${sysset.writes_val}","css":"font-size: 1.5rem;\nfont-weight: 500;","error":true}]},{"css":"flex: 0 0 auto;\nwidth: 16.375rem;\nheight: 3rem;\nfont-weight: 1.5;\ndisplay: flex;\nalign-items: center;\njustify-content: space-between;\ngap: 1rem;","layout":[{"format":"Reads","css":"flex: 0 0 auto;\nfont-weight: 100;\nfont-size: 1.5rem;\nheight: 1.75rem;\nwidth: 5rem;"},{"format":"${sysset.reads_val}","css":"font-size: 1.5rem;\nfont-weight: 500;","error":true}]}]},{"classes":"panel","css":"flex: 0 0 auto;\nflex-basis: 0 0 auto;\nwidth: 18rem;","layout":[{"classes":"container","css":"justify-content: center;\nheight: 3rem;\nfont-size: 2rem;\ncolor: #ffffff;\nbackground: #86a3ac;\ngap: 0.5rem;","layout":[{"css":"white-space: nowrap;\ntext-overflow: ellipsis;\nfont-weight: 700;","format":"MESH"}]},{"css":"height: 4rem;\ndisplay: flex;\nalign-items: center;\njustify-content: center;\ngap: 1rem;","layout":[{"format":"${sysset.nodetype_val}","css":"font-weight: 500;\nfont-size: 3rem;","error":true}]},{"css":"height: 2rem;\ndisplay: flex;\nalign-items: center;\njustify-content: space-between;\ngap: 1rem;","layout":[{"format":"MAC","css":"font-weight: 100;"},{"format":"${sysset.mac_val}","error":true}]},{"css":"height: 2rem;\ndisplay: flex;\nalign-items: center;\njustify-content: space-between;\ngap: 1rem;","layout":[{"format":"MESH","css":"flex: 0 0 auto;\nheight: 1.0625rem;\nwidth: 1.865234375rem;\nfont-weight: 100;"},{"format":"${sysset.mesh_val}","error":true}]}]},{"classes":"panel","css":"flex: 0 0 auto;\nheight: 14.5rem;\nflex-basis: 0 0 auto;\nwidth: 20.75rem;","layout":[{"classes":"container","css":"justify-content: center;\nheight: 3rem;\nfont-size: 2rem;\ncolor: #ffffff;\nbackground: #86a3ac;\ngap: 0.5rem;","layout":[{"css":"font-size: 2rem;\nwhite-space: nowrap;\ntext-overflow: ellipsis;\nfont-weight: 700;","format":"Comms"}]},{"css":"flex: 0 0 auto;\nheight: 1.75rem;\nwidth: 16.375rem;\ndisplay: flex;\nalign-items: center;\njustify-content: space-between;\ngap: 1rem;","layout":[{"format":"BytesIn","css":"font-size: 1.2rem;\nfont-weight: 100;\nborder-radius: 0rem;\nheight: 1.0625rem;"},{"format":"${sysset.bytesin_val}","css":"font-weight: 300;\nfont-size: 1.5rem;","error":true},{"format":"ByteOut","css":"font-size: 1.2rem;\nfont-weight: 100;\nheight: 1.0625rem;"},{"format":"${sysset.bytesout_val}","css":"font-weight: 300;\nfont-size: 1.5rem;","error":true}]},{"css":"flex: 0 0 auto;\nheight: 1.75rem;\nwidth: 16.375rem;\ndisplay: flex;\nalign-items: center;\njustify-content: space-between;\ngap: 1rem;","layout":[{"format":"BytesIn","css":"font-size: 1.2rem;\nfont-weight: 100;\nborder-radius: 0rem;\nheight: 1.0625rem;"},{"format":"${sysset.bytesin_val}","css":"font-weight: 300;\nfont-size: 1.5rem;","error":true},{"format":"ByteOut","css":"font-size: 1.2rem;\nfont-weight: 100;\nheight: 1.0625rem;"},{"format":"${sysset.bytesout_val}","css":"font-weight: 300;\nfont-size: 1.5rem;","error":true}]},{"css":"flex: 0 0 auto;\nheight: 1.75rem;\nwidth: 16.375rem;\ndisplay: flex;\nalign-items: center;\njustify-content: space-between;\ngap: 1rem;","layout":[{"format":"Conns","css":"flex: 0 0 auto;\nwidth: 3.736328125rem;\nfont-size: 1.2rem;\nfont-weight: 100;\nborder-radius: 0rem;\nheight: 1.4375rem;"},{"format":"${sysset.conns_val}","css":"font-weight: 300;\nfont-size: 1.5rem;","error":true},{"format":"Disco","css":"font-size: 1.2rem;\nfont-weight: 100;\nheight: 1.0625rem;"},{"format":"${sysset.disco_val}","css":"font-weight: 300;\nfont-size: 1.5rem;","error":true}]},{"css":"flex: 0 0 auto;\nheight: 1.75rem;\nwidth: 16.375rem;\ndisplay: flex;\nalign-items: center;\njustify-content: center;\ngap: 1rem;","layout":[{"format":"Date","css":"font-size: 1.2rem;\nfont-weight: 100;\nheight: 1.0625rem;"},{"format":"${sysset.ldate_val}","css":"height: 1.0625rem;","error":true}]}]}]},{"type":"action","title":"reboot","icon":"refresh","ref":"reboot","css":"flex: 0 0 auto;\nfont-size: 1.5rem;\nheight: 2.314453125rem;\nwidth: 76.25rem;","disabled":"${settings.disable_val>0}"}],"css":"height: 1.27734375rem;"},{"title":"ModBus Addresses","icon":"compose","css":"flex: 0 0 auto;\nflex-direction: column;\nflex-wrap: wrap;\nheight: 95.12890625rem;\nwidth: 35.75rem;\npadding: 0.75rem;\ngap: 0.5rem;\nmin-height: 2rem;\ndisplay: flex;\nflex-grow: 1;","layout":[{"classes":"panel","css":"flex: 0 0 auto;\nheight: 19.001953125rem;\nflex-basis: 0 0 auto;\nwidth: 39.375rem;","layout":[{"classes":"container","css":"flex: 0 0 auto;\nalign-items: center;\nheight: 3.25rem;\nwidth: 39.375rem;\njustify-content: center;\ncolor: #ffffff;\nbackground: #86a3ac;\ngap: 0.5rem;","layout":[{"type":"icon","icon":"fullscreen","css":"flex: 0 0 auto;\nwidth: 1.5rem;\nheight: 1.5rem;"},{"css":"flex: 0 0 auto;\nfont-size: 2rem;\nheight: 2.3876953125rem;\nwidth: 9.75rem;\nwhite-space: nowrap;\ntext-align: center;\ntext-overflow: ellipsis;\nfont-weight: 1200700;","format":"PV Panel"},{"type":"input","ref":"modbPanels.PVAddress","css":"flex: 0 0 auto;\ncolor: #e70808;\nwidth: 3rem;\nheight: 1.5625rem;\ntext-align: center;","input":"text"},{"format":"Refresh","css":"margin-left: 8.25rem;"},{"type":"input","ref":"modbPanels.refresh_rate","css":"flex: 0 0 auto;\ncolor: #e70808;\nwidth: 3rem;\nheight: 1.5625rem;\ntext-align: center;","input":"text"}]},{"classes":"container","css":"flex: 0 0 auto;\nwidth: 38rem;\nheight: 1.5rem;\nbackground: #a3b3b8;\ngap: 0.5rem;\nflex-wrap: wrap;","layout":[{"format":"Name","css":"margin-left: 0.5rem;\nmargin-top: 0.25rem;\nflex: 0 0 auto;\ncolor: #f7f7f7;\nheight: 1.0625rem;\nwidth: 2.3564453125rem;"},{"format":"Offset","css":"flex: 0 0 auto;\nmargin-left: 7.25rem;\nmargin-top: 0.25rem;\ncolor: #f7f7f7;\nheight: 1.0625rem;\nwidth: 2.634765625rem;"},{"format":"Start","css":"margin-left: 2.75rem;\nmargin-top: 0.25rem;\nflex: 0 0 auto;\ncolor: #f7f7f7;\nheight: 1.0625rem;\nwidth: 2.634765625rem;"},{"format":"Points","css":"margin-left: 3rem;\nmargin-top: 0.25rem;\nflex: 0 0 auto;\ncolor: #f7f7f7;\nheight: 1.0625rem;\nwidth: 2.634765625rem;"},{"format":"VType","css":"margin-left: 2.75rem;\nmargin-top: 0.25rem;\nflex: 0 0 auto;\ncolor: #f7f7f7;\nheight: 1.0625rem;\nwidth: 2.634765625rem;"},{"format":"Mux","css":"margin-left: 2.75rem;\nmargin-top: 0.25rem;\nflex: 0 0 auto;\ncolor: #f7f7f7;\nheight: 1.0625rem;\nwidth: 2.634765625rem;"}]},{"css":"height: 1.5625rem;\ndisplay: flex;\nalign-items: center;\njustify-content: space-between;\ngap: 1rem;","layout":[{"format":"Charging-State(C)","css":"flex: 0 0 auto;\nwidth: 7.5rem;\nheight: 1.0625rem;"},{"type":"input","ref":"modbPanels.Charge_StateOffset","css":"flex: 0 0 auto;\nwidth: 4rem;\nheight: 1.5625rem;\ntext-align: center;","input":"text"},{"type":"input","ref":"modbPanels.ChargeStart","css":"flex: 0 0 auto;\nwidth: 4rem;\nheight: 1.5625rem;\ntext-align: center;","input":"text"},{"type":"input","ref":"modbPanels.ChargePoints","css":"flex: 0 0 auto;\nwidth: 4rem;\nheight: 1.5625rem;\ntext-align: center;","input":"text"},{"type":"input","ref":"modbPanels.ChargeType","css":"flex: 0 0 auto;\nwidth: 4rem;\nheight: 1.5625rem;\ntext-align: center;","input":"text"},{"type":"input","ref":"modbPanels.ChargeMux","css":"flex: 0 0 auto;\nwidth: 4rem;\nheight: 1.5625rem;\ntext-align: center;","input":"number"}]},{"css":"height: 1.5625rem;\ndisplay: flex;\nalign-items: center;\njustify-content: space-between;\ngap: 1rem;","layout":[{"format":"PV1-Volts(V)","css":"flex: 0 0 auto;\nwidth: 7.5rem;\nheight: 1.0625rem;"},{"type":"input","ref":"modbPanels.PV1VoltsOffset","css":"flex: 0 0 auto;\nwidth: 4rem;\nheight: 1.5625rem;\ntext-align: center;"},{"type":"input","ref":"modbPanels.PV1VStart","css":"flex: 0 0 auto;\nwidth: 4rem;\nheight: 1.5625rem;\ntext-align: center;"},{"type":"input","ref":"modbPanels.PV1VPoints","css":"flex: 0 0 auto;\nwidth: 4rem;\nheight: 1.5625rem;\ntext-align: center;"},{"type":"input","ref":"modbPanels.PV1VType","css":"flex: 0 0 auto;\nwidth: 4rem;\nheight: 1.5625rem;\ntext-align: center;"},{"type":"input","ref":"modbPanels.PV1VMux","css":"flex: 0 0 auto;\nwidth: 4rem;\nheight: 1.5625rem;\ntext-align: center;","input":"number"}]},{"css":"height: 1.5625rem;\ndisplay: flex;\nalign-items: center;\njustify-content: space-between;\ngap: 1rem;","layout":[{"format":"PV2-Volts(V)","css":"flex: 0 0 auto;\nwidth: 7.5rem;\nheight: 1.0625rem;"},{"type":"input","ref":"modbPanels.PV2VoltsOffset","css":"flex: 0 0 auto;\nwidth: 4rem;\nheight: 1.5625rem;\ntext-align: center;"},{"type":"input","ref":"modbPanels.PV2VStart","css":"flex: 0 0 auto;\nwidth: 4rem;\nheight: 1.5625rem;\ntext-align: center;"},{"type":"input","ref":"modbPanels.PV2VPoints","css":"flex: 0 0 auto;\nwidth: 4rem;\nheight: 1.5625rem;\ntext-align: center;"},{"type":"input","ref":"modbPanels.PV2VoltsType","css":"flex: 0 0 auto;\nwidth: 4rem;\nheight: 1.5625rem;\ntext-align: center;"},{"type":"input","ref":"modbPanels.PV2VMux","css":"flex: 0 0 auto;\nwidth: 4rem;\nheight: 1.5625rem;\ntext-align: center;","input":"number"}]},{"css":"height: 1.5625rem;\ndisplay: flex;\nalign-items: center;\njustify-content: space-between;\ngap: 1rem;","layout":[{"format":"PV1-Amps(A)","css":"flex: 0 0 auto;\nwidth: 7.5rem;\nheight: 1.0625rem;"},{"type":"input","ref":"modbPanels.PV1_AmpsOffset","css":"flex: 0 0 auto;\nwidth: 4rem;\nheight: 1.5625rem;\ntext-align: center;"},{"type":"input","ref":"modbPanels.PV1AmpsStart","css":"flex: 0 0 auto;\nwidth: 4rem;\nheight: 1.5625rem;\ntext-align: center;"},{"type":"input","ref":"modbPanels.PV1AmpsPoints","css":"flex: 0 0 auto;\nwidth: 4rem;\nheight: 1.5625rem;\ntext-align: center;"},{"type":"input","ref":"modbPanels.PV1AmpsType","css":"flex: 0 0 auto;\nwidth: 4rem;\nheight: 1.5625rem;\ntext-align: center;"},{"type":"input","ref":"modbPanels.PV1AmpsMux","css":"flex: 0 0 auto;\nwidth: 4rem;\nheight: 1.5625rem;\ntext-align: center;","input":"number"}]},{"css":"display: flex;\nalign-items: center;\njustify-content: space-between;\ngap: 1rem;","layout":[{"format":"PV2-Amps(A)","css":"flex: 0 0 auto;\nwidth: 7.5rem;\nheight: 1.25rem;"},{"type":"input","ref":"modbPanels.PV2AmpsOffset","css":"flex: 0 0 auto;\nwidth: 4rem;\ntext-align: center;"},{"type":"input","ref":"modbPanels.PV2AmpsStart","css":"flex: 0 0 auto;\nwidth: 4rem;\ntext-align: center;"},{"type":"input","ref":"modbPanels.PV2AmpsPoints","css":"flex: 0 0 auto;\nwidth: 4rem;\ntext-align: center;"},{"type":"input","ref":"modbPanels.PV2AmpsType","css":"flex: 0 0 auto;\nwidth: 4rem;\ntext-align: center;"},{"type":"input","ref":"modbPanels.PV2AmpsMux","css":"flex: 0 0 auto;\nwidth: 4rem;\ntext-align: center;","input":"number"}]},{"classes":"container","css":"justify-content: center;\ngap: 0.5rem;\nflex-wrap: wrap;","layout":[{"type":"savebutton","title":"save panels","icon":"save","ref":"modbPanels"}]}]},{"classes":"panel","css":"flex: 0 0 auto;\nheight: 16.689453125rem;\nflex-basis: 0 0 auto;\nwidth: 39.375rem;","layout":[{"classes":"container","css":"flex: 0 0 auto;\nalign-items: center;\nwidth: 39.375rem;\nheight: 3.75rem;\njustify-content: center;\ncolor: #ffffff;\nbackground: #86a3ac;\ngap: 0.5rem;","layout":[{"type":"icon","icon":"work","css":"flex: 0 0 auto;\nwidth: 1.5rem;\nheight: 1.5rem;"},{"css":"flex: 0 0 auto;\nfont-size: 2rem;\nheight: 2.375rem;\nwidth: 8rem;\ntext-align: center;\nwhite-space: nowrap;\ntext-overflow: ellipsis;\nfont-weight: 700;","format":"Battery"},{"type":"input","ref":"modbBattery.batAddress","css":"flex: 0 0 auto;\ncolor: #ef0b0b;\nheight: 1.5625rem;\nwidth: 3rem;\ntext-align: center;","input":"text"},{"format":"Refresh","css":"margin-left: 9rem;\nheight: 1.0625rem;"},{"type":"input","ref":"modbBattery.refresh_rate","css":"flex: 0 0 auto;\ncolor: #ef0b0b;\nheight: 1.5625rem;\nwidth: 3rem;\ntext-align: center;","input":"text"}]},{"classes":"container","css":"flex: 0 0 auto;\nwidth: 38rem;\nheight: 1.5rem;\nbackground: #a3b3b8;\ngap: 0.5rem;\nflex-wrap: wrap;","layout":[{"format":"Name","css":"margin-left: 0.5rem;\nmargin-top: 0.25rem;\nflex: 0 0 auto;\ncolor: #f7f7f7;\nheight: 1.0625rem;\nwidth: 2.3564453125rem;"},{"format":"Offset","css":"margin-left: 6.25rem;\nmargin-top: 0.25rem;\nflex: 0 0 auto;\ncolor: #f7f7f7;\nheight: 1.0625rem;\nwidth: 2.634765625rem;"},{"format":"Start","css":"margin-left: 3rem;\nmargin-top: 0.25rem;\nflex: 0 0 auto;\ncolor: #f7f7f7;\nheight: 1.0625rem;\nwidth: 2.634765625rem;"},{"format":"Points","css":"margin-left: 3.25rem;\nmargin-top: 0.25rem;\nflex: 0 0 auto;\ncolor: #f7f7f7;\nheight: 1.0625rem;\nwidth: 2.634765625rem;"},{"format":"VType","css":"margin-left: 3.25rem;\nmargin-top: 0.25rem;\nflex: 0 0 auto;\ncolor: #f7f7f7;\nheight: 1.0625rem;\nwidth: 2.634765625rem;"},{"format":"Mux","css":"margin-left: 3rem;\nmargin-top: 0.25rem;\nflex: 0 0 auto;\ncolor: #f7f7f7;\nheight: 1.0625rem;\nwidth: 2.634765625rem;"}]},{"css":"height: 1.5625rem;\ndisplay: flex;\nalign-items: center;\njustify-content: space-between;\ngap: 1rem;","layout":[{"format":"SOC(%)","css":"flex: 0 0 auto;\nwidth: 6.5rem;\nheight: 1.0625rem;"},{"type":"input","ref":"modbBattery.SOCOffset","css":"flex: 0 0 auto;\nwidth: 4rem;\ntext-align: center;"},{"type":"input","ref":"modbBattery.SOCStart","css":"flex: 0 0 auto;\nwidth: 4rem;\ntext-align: center;"},{"type":"input","ref":"modbBattery.SOCPoints","css":"flex: 0 0 auto;\nheight: 1.5625rem;\nwidth: 4rem;\ntext-align: center;"},{"type":"input","ref":"modbBattery.SOCType","css":"flex: 0 0 auto;\nheight: 1.5625rem;\nwidth: 4rem;\ntext-align: center;"},{"type":"input","ref":"modbBattery.SOCMux","css":"flex: 0 0 auto;\nwidth: 4rem;\ntext-align: center;","input":"number"}]},{"css":"display: flex;\nalign-items: center;\njustify-content: space-between;\ngap: 1rem;","layout":[{"format":"SOH(%)","css":"flex: 0 0 auto;\nwidth: 6.25rem;\nheight: 1.25rem;"},{"type":"input","ref":"modbBattery.SOHOffset","css":"flex: 0 0 auto;\nwidth: 4rem;\ntext-align: center;"},{"type":"input","ref":"modbBattery.SOHStart","css":"flex: 0 0 auto;\nwidth: 4rem;\ntext-align: center;"},{"type":"input","ref":"modbBattery.SOHPoints","css":"flex: 0 0 auto;\nwidth: 4rem;\ntext-align: center;"},{"type":"input","ref":"modbBattery.SOHType","css":"flex: 0 0 auto;\nwidth: 4rem;\ntext-align: center;"},{"type":"input","ref":"modbBattery.SOHMux","css":"flex: 0 0 auto;\nwidth: 4rem;\ntext-align: center;","input":"number"}]},{"css":"display: flex;\nalign-items: center;\njustify-content: space-between;\ngap: 1rem;","layout":[{"format":"Cycle Count(#)","css":"flex: 0 0 auto;\nwidth: 6.25rem;\nheight: 1.0625rem;"},{"type":"input","ref":"modbBattery.cycleOffset","css":"flex: 0 0 auto;\nwidth: 4rem;\ntext-align: center;"},{"type":"input","ref":"modbBattery.cycleStart","css":"flex: 0 0 auto;\nwidth: 4rem;\ntext-align: center;"},{"type":"input","ref":"modbBattery.cyclePoints","css":"flex: 0 0 auto;\nwidth: 4rem;\ntext-align: center;"},{"type":"input","ref":"modbBattery.cycleType","css":"flex: 0 0 auto;\nwidth: 4rem;\ntext-align: center;"},{"type":"input","ref":"modbBattery.cycleMux","css":"flex: 0 0 auto;\nwidth: 4rem;\ntext-align: center;","input":"number"}]},{"css":"display: flex;\nalign-items: center;\njustify-content: space-between;\ngap: 1rem;","layout":[{"format":"BatTemp(˚C)","css":"flex: 0 0 auto;\nwidth: 6.25rem;\nheight: 1.0625rem;"},{"type":"input","ref":"modbBattery.tempOffset","css":"flex: 0 0 auto;\nwidth: 4rem;\ntext-align: center;"},{"type":"input","ref":"modbBattery.tempStart","css":"flex: 0 0 auto;\nwidth: 4rem;\ntext-align: center;"},{"type":"input","ref":"modbBattery.tempPoints","css":"flex: 0 0 auto;\nwidth: 4rem;\ntext-align: center;"},{"type":"input","ref":"modbBattery.tempType","css":"flex: 0 0 auto;\nwidth: 4rem;\ntext-align: center;"},{"type":"input","ref":"modbBattery.tempMux","css":"flex: 0 0 auto;\nwidth: 4rem;\ntext-align: center;","input":"number"}]},{"classes":"container","css":"justify-content: center;\ngap: 0.5rem;\nflex-wrap: wrap;","layout":[{"type":"savebutton","title":"save battery","icon":"save","ref":"modbBattery"}]}]},{"classes":"panel","css":"flex: 0 0 auto;\nheight: 19.001953125rem;\nflex-basis: 0 0 auto;\nwidth: 39.375rem;","layout":[{"classes":"container","css":"flex: 0 0 auto;\nalign-items: center;\nwidth: 39.25rem;\nheight: 4rem;\njustify-content: center;\ncolor: #ffffff;\nbackground: #86a3ac;\ngap: 0.5rem;","layout":[{"type":"icon","icon":"info","css":"flex: 0 0 auto;\nwidth: 1.5rem;\nheight: 1.5rem;"},{"css":"flex: 0 0 auto;\nfont-size: 2rem;\nheight: 2.375rem;\nwidth: 13rem;\ntext-align: center;\nwhite-space: nowrap;\ntext-overflow: ellipsis;\nfont-weight: 700;","format":"Sensors"},{"format":"Refresh","css":"margin-left: 9rem;\nheight: 1.0625rem;"},{"type":"input","ref":"modbSensors.refresh_rate","css":"flex: 0 0 auto;\ncolor: #f90606;\nheight: 1.5625rem;\nwidth: 3rem;"}]},{"classes":"container","css":"flex: 0 0 auto;\nalign-items: center;\nwidth: 38.25rem;\nheight: 1.5rem;\nbackground: #a3b3b8;\ngap: 0.5rem;\nflex-wrap: wrap;","layout":[{"format":"Name","css":"flex: 0 0 auto;\nmargin-left: 0.5rem;\nmargin-top: 0.25rem;\ncolor: #f7f7f7;\nheight: 1.0625rem;\nwidth: 2.3564453125rem;"},{"format":"Add","css":"margin-left: 3.25rem;\nmargin-top: 0.25rem;\nflex: 0 0 auto;\ncolor: #f7f7f7;\nheight: 1.0625rem;\nwidth: 2.3564453125rem;"},{"format":"Offset","css":"margin-left: 1.75rem;\nmargin-top: 0.25rem;\nflex: 0 0 auto;\ncolor: #f7f7f7;\nheight: 1.0625rem;\nwidth: 2.634765625rem;"},{"format":"Start","css":"margin-left: 2rem;\nmargin-top: 0.25rem;\nflex: 0 0 auto;\ncolor: #f7f7f7;\nheight: 1.0625rem;\nwidth: 2.634765625rem;"},{"format":"Points","css":"margin-left: 2.5rem;\nmargin-top: 0.25rem;\nflex: 0 0 auto;\ncolor: #f7f7f7;\nheight: 1.0625rem;\nwidth: 2.75rem;"},{"format":"VType","css":"margin-left: 3.5rem;\nmargin-top: 0.25rem;\nflex: 0 0 auto;\ncolor: #f7f7f7;\nheight: 1.0625rem;\nwidth: 2.5rem;"},{"format":"Mux","css":"flex: 0 0 auto;\nmargin-left: 2.5rem;\nmargin-top: 0.25rem;\ncolor: #f7f7f7;\nheight: 1.0625rem;\nwidth: 2.5rem;"}]},{"css":"height: 1.5625rem;\ndisplay: flex;\nalign-items: center;\njustify-content: space-between;\ngap: 1rem;","layout":[{"format":"DO(ppm)","css":"flex: 0 0 auto;\nwidth: 4rem;\nheight: 1.25rem;"},{"type":"input","ref":"modbSensors.DOAddress","css":"flex: 0 0 auto;\ncolor: #f60909;\nwidth: 3rem;\ntext-align: center;","input":"text"},{"type":"input","ref":"modbSensors.DOOffset","css":"flex: 0 0 auto;\nheight: 1.5625rem;\nwidth: 4rem;\ntext-align: center;","input":"text"},{"type":"input","ref":"modbSensors.DOStart","css":"flex: 0 0 auto;\nheight: 1.5625rem;\nwidth: 4rem;\ntext-align: center;","input":"text"},{"type":"input","ref":"modbSensors.DOPoints","css":"flex: 0 0 auto;\nheight: 1.5625rem;\nwidth: 4rem;\ntext-align: center;","input":"text"},{"type":"input","ref":"modbSensors.DOType","css":"flex: 0 0 auto;\nheight: 1.5625rem;\nwidth: 4rem;\ntext-align: center;","input":"text"},{"type":"input","ref":"modbSensors.DOMux","css":"flex: 0 0 auto;\nheight: 1.5625rem;\nwidth: 4rem;\ntext-align: center;","input":"number"}]},{"css":"display: flex;\nalign-items: center;\njustify-content: space-between;\ngap: 1rem;","layout":[{"format":" WTemp(˚C)","css":"flex: 0 0 auto;\nwidth: 3.75rem;\nheight: 1.0625rem;"},{"type":"input","ref":"modbSensors.WAddress","css":"flex: 0 0 auto;\ncolor: #f20707;\nwidth: 3rem;\ntext-align: center;","input":"text"},{"type":"input","ref":"modbSensors.WOffset","css":"flex: 0 0 auto;\nwidth: 4rem;\ntext-align: center;","input":"text"},{"type":"input","ref":"modbSensors.WStart","css":"flex: 0 0 auto;\nwidth: 4rem;\ntext-align: center;","input":"text"},{"type":"input","ref":"modbSensors.WPoints","css":"flex: 0 0 auto;\nwidth: 4rem;\ntext-align: center;","input":"text"},{"type":"input","ref":"modbSensors.WType","css":"flex: 0 0 auto;\nwidth: 4rem;\ntext-align: center;","input":"text"},{"type":"input","ref":"modbSensors.WMux","css":"flex: 0 0 auto;\nwidth: 4rem;\ntext-align: center;","input":"number"}]},{"css":"display: flex;\nalign-items: center;\njustify-content: space-between;\ngap: 1rem;","layout":[{"format":"Ph(#)","css":"flex: 0 0 auto;\nwidth: 3.5rem;\nheight: 1.0625rem;"},{"type":"input","ref":"modbSensors.PHAddress","css":"flex: 0 0 auto;\ncolor: #f40606;\nwidth: 3rem;\ntext-align: center;","input":"text"},{"type":"input","ref":"modbSensors.PHOffset","css":"flex: 0 0 auto;\nwidth: 4rem;\ntext-align: center;","input":"text"},{"type":"input","ref":"modbSensors.PHStart","css":"flex: 0 0 auto;\nwidth: 4rem;\ntext-align: center;","input":"text"},{"type":"input","ref":"modbSensors.PHPoints","css":"flex: 0 0 auto;\nwidth: 4rem;\ntext-align: center;","input":"text"},{"type":"input","ref":"modbSensors.PHType","css":"flex: 0 0 auto;\nwidth: 4rem;\ntext-align: center;","input":"text"},{"type":"input","ref":"modbSensors.PHMux","css":"flex: 0 0 auto;\nwidth: 4rem;\ntext-align: center;","input":"number"}]},{"css":"display: flex;\nalign-items: center;\njustify-content: space-between;\ngap: 1rem;","layout":[{"format":"ATemp(˚C)","css":"flex: 0 0 auto;\nwidth: 3.75rem;\nheight: 1.0625rem;"},{"type":"input","ref":"modbSensors.AAddress","css":"flex: 0 0 auto;\ncolor: #f70202;\nwidth: 3rem;\ntext-align: center;","input":"text"},{"type":"input","ref":"modbSensors.AOffset","css":"flex: 0 0 auto;\nwidth: 4rem;\ntext-align: center;","input":"text"},{"type":"input","ref":"modbSensors.AStart","css":"flex: 0 0 auto;\nwidth: 4rem;\ntext-align: center;","input":"text"},{"type":"input","ref":"modbSensors.APoints","css":"flex: 0 0 auto;\nwidth: 4rem;\ntext-align: center;","input":"text"},{"type":"input","ref":"modbSensors.AType","css":"flex: 0 0 auto;\nwidth: 4rem;\ntext-align: center;","input":"text"},{"type":"input","ref":"modbSensors.AMux","css":"flex: 0 0 auto;\nwidth: 4rem;\ntext-align: center;","input":"number"}]},{"css":"display: flex;\nalign-items: center;\njustify-content: space-between;\ngap: 1rem;","layout":[{"format":"Hum(%rH)","css":"flex: 0 0 auto;\nwidth: 3.609375rem;\nheight: 1.0625rem;"},{"type":"input","ref":"modbSensors.HAddress","css":"flex: 0 0 auto;\ncolor: #fa0505;\nwidth: 3rem;\ntext-align: center;","input":"text"},{"type":"input","ref":"modbSensors.HumOffset","css":"flex: 0 0 auto;\nwidth: 4rem;\ntext-align: center;","input":"text"},{"type":"input","ref":"modbSensors.humStart","css":"flex: 0 0 auto;\nwidth: 4rem;\ntext-align: center;","input":"text"},{"type":"input","ref":"modbSensors.humPoints","css":"flex: 0 0 auto;\nwidth: 4rem;\ntext-align: center;","input":"text"},{"type":"input","ref":"modbSensors.humType","css":"flex: 0 0 auto;\nwidth: 4rem;\ntext-align: center;","input":"text"},{"type":"input","ref":"modbSensors.humMux","css":"flex: 0 0 auto;\nwidth: 4rem;\ntext-align: center;","input":"number"}]},{"classes":"container","css":"height: 1.564453125rem;\njustify-content: center;\ngap: 0.5rem;\nflex-wrap: wrap;","layout":[{"type":"savebutton","title":"save sensors","icon":"save","ref":"modbSensors"}]}]},{"classes":"panel","css":"flex: 0 0 auto;\nwidth: 39.375rem;\nheight: 29.314453125rem;\nflex-basis: 0 0 auto;","layout":[{"classes":"container","css":"flex: 0 0 auto;\nalign-items: center;\nheight: 4rem;\nwidth: 39.375rem;\njustify-content: center;\ncolor: #ffffff;\nbackground: #86a3ac;\ngap: 0.5rem;","layout":[{"type":"icon","icon":"lightning","css":"flex: 0 0 auto;\nwidth: 1.5rem;\nheight: 1.5rem;","__label":"icon"},{"css":"flex: 0 0 auto;\nmargin-left: 1rem;\nfont-size: 2rem;\nheight: 2.3876953125rem;\ntext-align: center;\nwidth: 7.3115234375rem;\nwhite-space: nowrap;\ntext-overflow: ellipsis;\nfont-weight: 700;","format":"Inverter"},{"type":"input","ref":"modbInverter.InverterAddress","css":"flex: 0 0 auto;\ncolor: #fa0505;\nmargin-left: 1.5rem;\nheight: 1.5625rem;\nwidth: 3rem;\ntext-align: center;","input":"text"},{"format":"Refresh","css":"margin-left: 9rem;"},{"type":"input","ref":"modbInverter.refresh_rate","css":"flex: 0 0 auto;\ncolor: #fa0505;\nheight: 1.5625rem;\nwidth: 3rem;\ntext-align: center;","input":"text"}]},{"classes":"container","css":"flex: 0 0 auto;\nwidth: 38rem;\nheight: 1.5rem;\nbackground: #a3b3b8;\ngap: 0.5rem;\nflex-wrap: wrap;","layout":[{"format":"Name","css":"margin-left: 0.5rem;\nmargin-top: 0.25rem;\nflex: 0 0 auto;\ncolor: #f7f7f7;\nheight: 1.0625rem;\nwidth: 2.3564453125rem;"},{"format":"Offset","css":"margin-left: 7.5rem;\nmargin-top: 0.25rem;\nflex: 0 0 auto;\ncolor: #f7f7f7;\nheight: 1.0625rem;\nwidth: 2.634765625rem;"},{"format":"Start","css":"margin-left: 2.5rem;\nmargin-top: 0.25rem;\nflex: 0 0 auto;\ncolor: #f7f7f7;\nheight: 1.0625rem;\nwidth: 2.634765625rem;"},{"format":"Points","css":"flex: 0 0 auto;\nmargin-left: 3rem;\nmargin-top: 0.25rem;\ncolor: #f7f7f7;\nheight: 1.0625rem;\nwidth: 2.634765625rem;"},{"format":"VType","css":"flex: 0 0 auto;\nmargin-left: 2.75rem;\nmargin-top: 0.25rem;\ncolor: #f7f7f7;\nheight: 1.0625rem;\nwidth: 2.25rem;"},{"format":"Mux","css":"margin-left: 3.25rem;\nmargin-top: 0.25rem;\nflex: 0 0 auto;\ncolor: #f7f7f7;\nheight: 1.0625rem;\nwidth: 2.25rem;"}]},{"css":"height: 1.5625rem;\ndisplay: flex;\nalign-items: center;\njustify-content: space-between;\ngap: 1rem;","layout":[{"format":"I1_BatChHoy(kw)","css":"flex: 0 0 auto;\nwidth: 7.75rem;\nheight: 1.25rem;"},{"type":"input","ref":"modbInverter.I1_BatChHoyOff","css":"flex: 0 0 auto;\nwidth: 4rem;\ntext-align: center;"},{"type":"input","ref":"modbInverter.I1_BatChHoyStart","css":"flex: 0 0 auto;\nwidth: 4rem;\ntext-align: center;"},{"type":"input","ref":"modbInverter.I1_BatChHoyPoints","css":"flex: 0 0 auto;\nwidth: 4rem;\ntext-align: center;"},{"type":"input","ref":"modbInverter.I1_BatChHoyType","css":"flex: 0 0 auto;\nwidth: 4rem;\ntext-align: center;"},{"type":"input","ref":"modbInverter.I1_BatChHoyMux","css":"flex: 0 0 auto;\nwidth: 4rem;\ntext-align: center;","input":"number"}]},{"css":"display: flex;\nalign-items: center;\njustify-content: space-between;\ngap: 1rem;","layout":[{"format":"I2_BatDscHoy(kw)","css":"flex: 0 0 auto;\nwidth: 7.75rem;\nheight: 1.25rem;"},{"type":"input","ref":"modbInverter.I2_BatDscHoyOff","css":"flex: 0 0 auto;\nwidth: 4rem;\ntext-align: center;"},{"type":"input","ref":"modbInverter.I2_BatDscHoyStart","css":"flex: 0 0 auto;\nwidth: 4rem;\ntext-align: center;"},{"type":"input","ref":"modbInverter.I2_BatDscHoyPoints","css":"flex: 0 0 auto;\nwidth: 4rem;\ntext-align: center;"},{"type":"input","ref":"modbInverter.I2_BatDscHoyType","css":"flex: 0 0 auto;\nwidth: 4rem;\ntext-align: center;"},{"type":"input","ref":"modbInverter.I2_BatDscHoyMux","css":"flex: 0 0 auto;\nwidth: 4rem;\ntext-align: center;","input":"number"}]},{"css":"display: flex;\nalign-items: center;\njustify-content: space-between;\ngap: 1rem;","layout":[{"format":"I3_BatChgTotal(kw)","css":"flex: 0 0 auto;\nwidth: 7.75rem;\nheight: 1.0625rem;"},{"type":"input","ref":"modbInverter.I3_BatChgTotalOff","css":"flex: 0 0 auto;\nwidth: 4rem;\ntext-align: center;"},{"type":"input","ref":"modbInverter.I3_BatChgTotalStart","css":"flex: 0 0 auto;\nwidth: 4rem;\ntext-align: center;"},{"type":"input","ref":"modbInverter.I3_BatChgTotalPoints","css":"flex: 0 0 auto;\nwidth: 4rem;\ntext-align: center;"},{"type":"input","ref":"modbInverter.I3_BatChgTotalType","css":"flex: 0 0 auto;\nwidth: 4rem;\ntext-align: center;"},{"type":"input","ref":"modbInverter.I3_BatChgTotalMux","css":"flex: 0 0 auto;\nwidth: 4rem;\ntext-align: center;","input":"number"}]},{"css":"display: flex;\nalign-items: center;\njustify-content: space-between;\ngap: 1rem;","layout":[{"format":"I4_BatDscTotal(kw)","css":"flex: 0 0 auto;\nwidth: 7.75rem;\nheight: 1.0625rem;"},{"type":"input","ref":"modbInverter.I4_BatDscTotalOff","css":"flex: 0 0 auto;\nwidth: 4rem;\ntext-align: center;"},{"type":"input","ref":"modbInverter.I4_BatDscTotalStart","css":"flex: 0 0 auto;\nwidth: 4rem;\ntext-align: center;"},{"type":"input","ref":"modbInverter.I4_BatDscTotalPoints","css":"flex: 0 0 auto;\nwidth: 4rem;\ntext-align: center;"},{"type":"input","ref":"modbInverter.I4_BatDscTotalType","css":"flex: 0 0 auto;\nwidth: 4rem;\ntext-align: center;"},{"type":"input","ref":"modbInverter.I4_BatDscTotalMux","css":"flex: 0 0 auto;\nwidth: 4rem;\ntext-align: center;","input":"number"}]},{"css":"display: flex;\nalign-items: center;\njustify-content: space-between;\ngap: 1rem;","layout":[{"format":"I5_GenkWhHoy(kw)","css":"flex: 0 0 auto;\nwidth: 8rem;\nheight: 1.25rem;"},{"type":"input","ref":"modbInverter.I5_GenkWhHoyOff","css":"flex: 0 0 auto;\nwidth: 4rem;\ntext-align: center;"},{"type":"input","ref":"modbInverter.I5_GenkWhHoyStart","css":"flex: 0 0 auto;\nwidth: 4rem;\ntext-align: center;"},{"type":"input","ref":"modbInverter.I5_GenkWhHoyPoints","css":"flex: 0 0 auto;\nwidth: 4rem;\ntext-align: center;"},{"type":"input","ref":"modbInverter.I5_GenkWhHoyType","css":"flex: 0 0 auto;\nwidth: 4rem;\ntext-align: center;"},{"type":"input","ref":"modbInverter.I5_GenkWhHoyMux","css":"flex: 0 0 auto;\nwidth: 4rem;\ntext-align: center;","input":"number"}]},{"css":"display: flex;\nalign-items: center;\njustify-content: space-between;\ngap: 1rem;","layout":[{"format":"I6_GLoadUsedHoy(kw)","css":"flex: 0 0 auto;\nwidth: 8rem;\nheight: 1.0625rem;"},{"type":"input","ref":"modbInverter.I6_UsedkwhHoyOff","css":"flex: 0 0 auto;\nwidth: 4rem;\ntext-align: center;"},{"type":"input","ref":"modbInverter.I6_UsedkwhHoyStart","css":"flex: 0 0 auto;\nwidth: 4rem;\ntext-align: center;"},{"type":"input","ref":"modbInverter.I6_UsedkwhHoyPoints","css":"flex: 0 0 auto;\nwidth: 4rem;\ntext-align: center;"},{"type":"input","ref":"modbInverter.I6_UsedkwhHoyType","css":"flex: 0 0 auto;\nwidth: 4rem;\ntext-align: center;"},{"type":"input","ref":"modbInverter.I6_UsedkwhHoyMux","css":"flex: 0 0 auto;\nwidth: 4rem;\ntext-align: center;","input":"number"}]},{"css":"display: flex;\nalign-items: center;\njustify-content: space-between;\ngap: 1rem;","layout":[{"format":"I7_GLoadUsedTot(kWh)","css":"flex: 0 0 auto;\nwidth: 8rem;\nheight: 1.0625rem;"},{"type":"input","ref":"modbInverter.I7_LoadUsedTotalOff","css":"flex: 0 0 auto;\nwidth: 4rem;\ntext-align: center;"},{"type":"input","ref":"modbInverter.I7_LoadUsedTotalStart","css":"flex: 0 0 auto;\nwidth: 4rem;\ntext-align: center;"},{"type":"input","ref":"modbInverter.I7_LoadUsedTotalPoints","css":"flex: 0 0 auto;\nwidth: 4rem;\ntext-align: center;"},{"type":"input","ref":"modbInverter.I7_LoadUsedTotalType","css":"flex: 0 0 auto;\nwidth: 4rem;\ntext-align: center;"},{"type":"input","ref":"modbInverter.I7_LoadUsedTotalMux","css":"flex: 0 0 auto;\nwidth: 4rem;\ntext-align: center;","input":"number"}]},{"css":"display: flex;\nalign-items: center;\njustify-content: space-between;\ngap: 1rem;","layout":[{"format":"I8_BattChdHoy(A)","css":"flex: 0 0 auto;\nwidth: 7.75rem;\nheight: 1.0625rem;"},{"type":"input","ref":"modbInverter.I8_BatChdHoyOff","css":"flex: 0 0 auto;\nwidth: 4rem;\ntext-align: center;"},{"type":"input","ref":"modbInverter.I8_BatChdHoyStart","css":"flex: 0 0 auto;\nwidth: 4rem;\ntext-align: center;"},{"type":"input","ref":"modbInverter.I8_BatChdHoyPoints","css":"flex: 0 0 auto;\nwidth: 4rem;\ntext-align: center;"},{"type":"input","ref":"modbInverter.I8_BatChdHoyType","css":"flex: 0 0 auto;\nwidth: 4rem;\ntext-align: center;"},{"type":"input","ref":"modbInverter.I8_BatChdHoyMux","css":"flex: 0 0 auto;\nwidth: 4rem;\ntext-align: center;","input":"number"}]},{"css":"display: flex;\nalign-items: center;\njustify-content: space-between;\ngap: 1rem;","layout":[{"format":"I9_BattDscHoy(A)","css":"flex: 0 0 auto;\nwidth: 8rem;\nheight: 1.0625rem;"},{"type":"input","ref":"modbInverter.I9_BatDscHoyOff","css":"flex: 0 0 auto;\nwidth: 4rem;\ntext-align: center;"},{"type":"input","ref":"modbInverter.I9_BatDscHoyStart","css":"flex: 0 0 auto;\nwidth: 4rem;\ntext-align: center;"},{"type":"input","ref":"modbInverter.I9_BatDscHoyPoints","css":"flex: 0 0 auto;\nwidth: 4rem;\ntext-align: center;"},{"type":"input","ref":"modbInverter.I9_BatDscHoyType","css":"flex: 0 0 auto;\nwidth: 4rem;\ntext-align: center;"},{"type":"input","ref":"modbInverter.I9_BatDscHoyMux","css":"flex: 0 0 auto;\nwidth: 4rem;\ntext-align: center;","input":"number"}]},{"css":"height: 1.5625rem;\ndisplay: flex;\nalign-items: center;\njustify-content: space-between;\ngap: 1rem;","layout":[{"format":"I10_LoadGTot(kWh)","css":"flex: 0 0 auto;\nwidth: 7.9443359375rem;\nheight: 1.25rem;"},{"type":"input","ref":"modbInverter.I10_LoadUsedHoyOff","css":"flex: 0 0 auto;\nheight: 1.5625rem;\nwidth: 4rem;\ntext-align: center;"},{"type":"input","ref":"modbInverter.I10_LoadUsedHoyStart","css":"flex: 0 0 auto;\nheight: 1.5625rem;\nwidth: 4rem;\ntext-align: center;"},{"type":"input","ref":"modbInverter.I10_LoadUsedHoyPoints","css":"flex: 0 0 auto;\nheight: 1.5625rem;\nwidth: 4rem;\ntext-align: center;"},{"type":"input","ref":"modbInverter.I10_LoadUsedHoyType","css":"flex: 0 0 auto;\nheight: 1.5625rem;\nwidth: 4rem;\ntext-align: center;"},{"type":"input","ref":"modbInverter.I10_LoadUsedHoyMux","css":"flex: 0 0 auto;\nheight: 1.5625rem;\nwidth: 4rem;\ntext-align: center;","input":"number"}]},{"classes":"container","css":"justify-content: center;\ngap: 0.5rem;\nflex-wrap: wrap;","layout":[{"type":"savebutton","title":"save inverter","icon":"save","ref":"modbInverter"},{"type":"action","title":"reboot","icon":"refresh","ref":"reboot","disabled":"${settings.disable_val>0}"}]}]}]},{"title":"PID Controller","icon":"location","css":"padding: 0.75rem;\ngap: 0.5rem;\nmin-height: 2rem;\ndisplay: flex;\nflex-direction: column;\nflex-grow: 1;","layout":[{"classes":"panel","css":"flex: 0 0 auto;\nheight: 17.3515625rem;\nflex-basis: 0 0 auto;\nwidth: 26.75rem;","layout":[{"classes":"container","css":"justify-content: center;\nbackground: #86a3ac;\nheight: 3.25rem;\ncolor: #fefbfb;\nflex-wrap: wrap;","layout":[{"format":"PID Controller","css":"font-size: 2rem;"}]},{"classes":"container","css":"justify-content: center;\ngap: 0.5rem;\nflex-wrap: wrap;","layout":[{"format":"DO SetPoint","css":"color: #e65656;\nfont-weight: 900;\nfont-size: 1.5rem;\nheight: 1.75rem;"},{"type":"input","ref":"DO.setpoint","css":"font-weight: 900;\nflex: 0 0 auto;\nwidth: 4rem;"}]},{"css":"background: #86a3ac;\nalign-items: center;\ndisplay: flex;\ngap: 1rem;","layout":[{"format":"KP","css":"margin-left: 3rem;\nflex: 0 0 auto;\nfont-weight: 900;\nheight: 1.0625rem;\nwidth: 1.5rem;"},{"type":"input","ref":"DO.KP","css":"flex: 0 0 auto;\nwidth: 3.5rem;\nheight: 1.5625rem;"},{"format":"KI","css":"flex: 0 0 auto;\nfont-weight: 900;\nheight: 1.25rem;\nwidth: 0.939453125rem;"},{"type":"input","ref":"DO.KI","css":"flex: 0 0 auto;\nwidth: 3.5rem;\nheight: 1.5625rem;"},{"format":"KD","css":"flex: 0 0 auto;\nfont-weight: 900;\nheight: 1.25rem;\nwidth: 1.2978515625rem;"},{"type":"input","ref":"DO.KD","css":"flex: 0 0 auto;\nwidth: 3.5rem;\nheight: 1.5625rem;"}]},{"classes":"container","css":"align-items: center;\njustify-content: space-between;\ngap: 0.5rem;\nflex-wrap: wrap;","layout":[{"format":"Allow DO Control","css":"flex: 0 0 auto;\nwidth: 8.29296875rem;\nheight: 1.0625rem;"},{"type":"toggle","ref":"DO.docontrol"},{"format":"Night Only","css":"flex: 0 0 auto;\nwidth: 4.5rem;\nheight: 1.0625rem;"},{"type":"toggle","ref":"DO.nighonly"}]},{"classes":"container","css":"flex: 0 0 auto;\njustify-content: space-between;\nalign-items: center;\nheight: 3.5rem;\nwidth: 25.125rem;\ngap: 0.5rem;\nflex-wrap: wrap;","layout":[{"format":"Sample Time(mins)","css":"flex: 0 0 auto;\nheight: 1.75rem;\nwidth: 13.25rem;\nfont-size: 1.5rem;"},{"type":"input","ref":"DO.sampletime","input":"number","css":"flex: 0 0 auto;\nheight: 1.5625rem;\nwidth: 4rem;"}]},{"css":"margin-top: 0.25rem;\njustify-content: space-between;\ndisplay: flex;\nalign-items: center;\ngap: 1rem;","layout":[{"type":"action","title":"reboot","icon":"refresh","ref":"reboot","css":"flex: 0 0 auto;\nwidth: 7.7919921875rem;\nfont-size: 1.5rem;\nheight: 2.314453125rem;","disabled":"${settings.disable_val>0}"},{"type":"savebutton","ref":"DO","title":"save","icon":"save","css":"font-size: 1.5rem;\nheight: 2.314453125rem;"}]}]}]},{"title":"Limits","icon":"zoom-in","classes":"page","layout":[{"classes":"container","css":"gap: 0.5rem;\nflex-wrap: wrap;","layout":[{"classes":"panel","css":"flex: 0 0 auto;\nheight: 6.75rem;\nflex-basis: 0 0 auto;\nwidth: 20.5rem;","layout":[{"classes":"container","css":"flex-direction: column;\nalign-items: center;\ncolor: #ffffff;\nbackground: #86a3ac;\njustify-content: center;\nheight: 4rem;\ngap: 0.5rem;","layout":[{"css":"font-size: 3rem;\nwhite-space: nowrap;\ntext-overflow: ellipsis;\nfont-weight: 700;","format":"PV Panels"}]},{"classes":"container","css":"justify-content: center;\nalign-items: center;\ngap: 0.5rem;\nflex-wrap: wrap;","layout":[{"format":"Volts","__label":"text","css":"color: #304fe8;\nflex: 0 0 auto;\nwidth: 2.005859375rem;\nheight: 1.0625rem;"},{"type":"input","ref":"limits.vmin","css":"flex: 0 0 auto;\nheight: 1.5625rem;\nwidth: 3rem;"},{"type":"input","ref":"limits.vmax","css":"flex: 0 0 auto;\nheight: 1.5625rem;\nwidth: 3rem;"},{"format":"Amps","__label":"text","css":"color: #ba4f4f;\nheight: 1.0625rem;"},{"type":"input","ref":"limits.amin","css":"flex: 0 0 auto;\nheight: 1.5625rem;\nwidth: 3rem;"},{"type":"input","ref":"limits.amax","css":"flex: 0 0 auto;\nheight: 1.5625rem;\nwidth: 3rem;"}]}]},{"classes":"panel","css":"flex: 0 0 auto;\nheight: 13rem;\nflex-basis: 0 0 auto;\nwidth: 20.5rem;","layout":[{"classes":"container","css":"align-items: center;\ncolor: #ffffff;\nbackground: #86a3ac;\njustify-content: center;\nheight: 4rem;\ngap: 0.5rem;","layout":[{"css":"font-size: 3rem;\nwhite-space: nowrap;\ntext-overflow: ellipsis;\nfont-weight: 700;","format":"Battery"}]},{"classes":"container","css":"justify-content: center;\nalign-items: center;\ngap: 0.5rem;\nflex-wrap: wrap;","layout":[{"format":"SOC","__label":"text","css":"flex: 0 0 auto;\ncolor: #304fe8;\nwidth: 10rem;\nheight: 1.0625rem;"},{"type":"input","ref":"limits.bSOCmin","css":"flex: 0 0 auto;\nheight: 1.5625rem;\nwidth: 3rem;"},{"type":"input","ref":"limits.bSOCmax","css":"flex: 0 0 auto;\nheight: 1.5625rem;\nwidth: 3rem;"},{"format":"%","__label":"text","css":"height: 1.0625rem;"}]},{"classes":"container","css":"justify-content: center;\nalign-items: center;\ngap: 0.5rem;\nflex-wrap: wrap;","layout":[{"format":"SOH","__label":"text","css":"flex: 0 0 auto;\ncolor: #304fe8;\nwidth: 10rem;\nheight: 1.0625rem;"},{"type":"input","ref":"limits.bSOHmin","css":"flex: 0 0 auto;\nheight: 1.5625rem;\nwidth: 3rem;"},{"type":"input","ref":"limits.bSOHmax","css":"flex: 0 0 auto;\nheight: 1.5625rem;\nwidth: 3rem;"},{"format":"%","__label":"text","css":"height: 1.0625rem;"}]},{"classes":"container","css":"justify-content: center;\nalign-items: center;\ngap: 0.5rem;\nflex-wrap: wrap;","layout":[{"format":"Cycles","__label":"text","css":"flex: 0 0 auto;\ncolor: #304fe8;\nwidth: 10rem;\nheight: 1.0625rem;"},{"type":"input","ref":"limits.bcyclemin","css":"flex: 0 0 auto;\nheight: 1.5625rem;\nwidth: 3rem;"},{"type":"input","ref":"limits.bcyclemax","css":"flex: 0 0 auto;\nheight: 1.5625rem;\nwidth: 3rem;"},{"format":"#","__label":"text","css":"height: 1.0625rem;"}]},{"classes":"container","css":"justify-content: center;\nalign-items: center;\ngap: 0.5rem;\nflex-wrap: wrap;","layout":[{"format":"Temp","__label":"text","css":"flex: 0 0 auto;\ncolor: #304fe8;\nwidth: 10rem;\nheight: 1.0625rem;"},{"type":"input","ref":"limits.btempmin","css":"flex: 0 0 auto;\nheight: 1.5625rem;\nwidth: 3rem;"},{"type":"input","ref":"limits.btempmax","css":"flex: 0 0 auto;\nheight: 1.5625rem;\nwidth: 3rem;"},{"format":"˚C","__label":"text","css":"flex: 0 0 auto;\nheight: 1.0625rem;\nwidth: 0.6171875rem;"}]}]},{"classes":"panel","css":"flex: 0 0 auto;\nheight: 13.25rem;\nflex-basis: 0 0 auto;\nwidth: 20.5rem;","layout":[{"classes":"container","css":"align-items: center;\ncolor: #ffffff;\nbackground: #86a3ac;\njustify-content: center;\nheight: 4rem;\ngap: 0.5rem;","layout":[{"css":"flex: 0 0 auto;\nwidth: 6.5126953125rem;\nfont-size: 3rem;\nwhite-space: nowrap;\ntext-overflow: ellipsis;\nfont-weight: 700;","format":"Amps"}]},{"classes":"container","css":"justify-content: center;\nalign-items: center;\ngap: 0.5rem;\nflex-wrap: wrap;","layout":[{"format":"Charge Today","__label":"text","css":"flex: 0 0 auto;\ntext-align: left;\ncolor: #304fe8;\nwidth: 11.5rem;\nheight: 1.25rem;"},{"type":"input","ref":"limits.bcAhoymin","css":"flex: 0 0 auto;\nheight: 1.5625rem;\nwidth: 3rem;"},{"type":"input","ref":"limits.bcAhoymax","css":"flex: 0 0 auto;\nheight: 1.5625rem;\nwidth: 3rem;"}]},{"classes":"container","css":"justify-content: center;\nalign-items: center;\ngap: 0.5rem;\nflex-wrap: wrap;","layout":[{"format":"Discharge Today","__label":"text","css":"flex: 0 0 auto;\ncolor: #304fe8;\nwidth: 11.5rem;\nheight: 1.0625rem;"},{"type":"input","ref":"limits.bdAhoymin","css":"flex: 0 0 auto;\nheight: 1.5625rem;\nwidth: 3rem;"},{"type":"input","ref":"limits.bdAhoymax","css":"flex: 0 0 auto;\nheight: 1.5625rem;\nwidth: 3rem;"}]},{"classes":"container","css":"justify-content: center;\nalign-items: center;\ngap: 0.5rem;\nflex-wrap: wrap;","layout":[{"format":"Charge Total","__label":"text","css":"flex: 0 0 auto;\ncolor: #304fe8;\nwidth: 11.5rem;\nheight: 1.0625rem;"},{"type":"input","ref":"limits.bcATotmin","css":"flex: 0 0 auto;\nheight: 1.5625rem;\nwidth: 3rem;"},{"type":"input","ref":"limits.bcATotmax","css":"flex: 0 0 auto;\nheight: 1.5625rem;\nwidth: 3rem;"}]},{"classes":"container","css":"justify-content: center;\nalign-items: center;\ngap: 0.5rem;\nflex-wrap: wrap;","layout":[{"format":"Discharge Total","__label":"text","css":"flex: 0 0 auto;\ncolor: #304fe8;\nwidth: 11.5rem;\nheight: 1.0625rem;"},{"type":"input","ref":"limits.bdATotmin","css":"flex: 0 0 auto;\nheight: 1.5625rem;\nwidth: 3rem;"},{"type":"input","ref":"limits.bdATotmax","css":"flex: 0 0 auto;\nheight: 1.5625rem;\nwidth: 3rem;"}]}]},{"classes":"panel","css":"flex: 0 0 auto;\nheight: 17.25rem;\nflex-basis: 0 0 auto;\nwidth: 20.5rem;","layout":[{"classes":"container","css":"align-items: center;\ncolor: #ffffff;\nbackground: #86a3ac;\njustify-content: center;\nheight: 4rem;\ngap: 0.5rem;","layout":[{"css":"font-size: 3rem;\nwhite-space: nowrap;\ntext-overflow: ellipsis;\nfont-weight: 700;","format":"kWh"}]},{"classes":"container","css":"justify-content: center;\nalign-items: center;\ngap: 0.5rem;\nflex-wrap: wrap;","layout":[{"format":"Generated Today","__label":"text","css":"flex: 0 0 auto;\ncolor: #304fe8;\nwidth: 11.5rem;\nheight: 1.25rem;"},{"type":"input","ref":"limits.kwgtodaymin","css":"flex: 0 0 auto;\nheight: 1.5625rem;\nwidth: 3rem;"},{"type":"input","ref":"limits.kwgtodaymax","css":"flex: 0 0 auto;\nheight: 1.5625rem;\nwidth: 3rem;"}]},{"classes":"container","css":"justify-content: center;\nalign-items: center;\ngap: 0.5rem;\nflex-wrap: wrap;","layout":[{"format":"Consumed Today","__label":"text","css":"flex: 0 0 auto;\ncolor: #304fe8;\nwidth: 11.5rem;\nheight: 1.25rem;"},{"type":"input","ref":"limits.kwctodaymin","css":"flex: 0 0 auto;\nheight: 1.5625rem;\nwidth: 3rem;"},{"type":"input","ref":"limits.kwctodaymax","css":"flex: 0 0 auto;\nheight: 1.5625rem;\nwidth: 3rem;"}]},{"classes":"container","css":"justify-content: center;\nalign-items: center;\ngap: 0.5rem;\nflex-wrap: wrap;","layout":[{"format":"Load Comsumed Today","__label":"text","css":"flex: 0 0 auto;\ncolor: #304fe8;\nwidth: 11.5rem;\nheight: 1.25rem;"},{"type":"input","ref":"limits.kwloadhoymin","css":"flex: 0 0 auto;\nheight: 1.5625rem;\nwidth: 3rem;"},{"type":"input","ref":"limits.kwloadhoymax","css":"flex: 0 0 auto;\nheight: 1.5625rem;\nwidth: 3rem;"}]},{"classes":"container","css":"justify-content: center;\nalign-items: center;\ngap: 0.5rem;\nflex-wrap: wrap;","layout":[{"format":"Load Consumed Total","__label":"text","css":"flex: 0 0 auto;\ncolor: #304fe8;\nwidth: 11.5rem;\nheight: 1.25rem;"},{"type":"input","ref":"limits.kwchoymin","css":"flex: 0 0 auto;\nheight: 1.5625rem;\nwidth: 3rem;"},{"type":"input","ref":"limits.kwchoymax","css":"flex: 0 0 auto;\nheight: 1.5625rem;\nwidth: 3rem;"}]},{"classes":"container","css":"justify-content: center;\nalign-items: center;\ngap: 0.5rem;\nflex-wrap: wrap;","layout":[{"format":"Battery Charge Today","__label":"text","css":"flex: 0 0 auto;\ncolor: #304fe8;\nwidth: 11.5rem;\nheight: 1.25rem;"},{"type":"input","ref":"limits.kwbatchoymin","css":"flex: 0 0 auto;\nheight: 1.5625rem;\nwidth: 3rem;"},{"type":"input","ref":"limits.kwbatchoymax","css":"flex: 0 0 auto;\nheight: 1.5625rem;\nwidth: 3rem;"}]},{"classes":"container","css":"justify-content: center;\nalign-items: center;\ngap: 0.5rem;\nflex-wrap: wrap;","layout":[{"format":"Battery Discharge Today","__label":"text","css":"flex: 0 0 auto;\ncolor: #304fe8;\nwidth: 11.5rem;\nheight: 1.25rem;"},{"type":"input","ref":"limits.kwbatdhoymin","css":"flex: 0 0 auto;\nheight: 1.5625rem;\nwidth: 3rem;"},{"type":"input","ref":"limits.kwbatdhoymax","css":"flex: 0 0 auto;\nheight: 1.5625rem;\nwidth: 3rem;"}]}]},{"classes":"panel","css":"flex: 0 0 auto;\nheight: 15.5rem;\nflex-basis: 0 0 auto;\nwidth: 20.5rem;","layout":[{"classes":"container","css":"align-items: center;\ncolor: #ffffff;\nbackground: #86a3ac;\njustify-content: center;\nheight: 4rem;\ngap: 0.5rem;","layout":[{"css":"font-size: 3rem;\nwhite-space: nowrap;\ntext-overflow: ellipsis;\nfont-weight: 700;","format":"Sensors"}]},{"classes":"container","css":"justify-content: center;\nalign-items: center;\ngap: 0.5rem;\nflex-wrap: wrap;","layout":[{"format":"Dissolved Oxygen","__label":"text","css":"flex: 0 0 auto;\ncolor: #304fe8;\nwidth: 9.25rem;\nheight: 1.5rem;"},{"type":"input","ref":"limits.domin","css":"flex: 0 0 auto;\nheight: 1.5625rem;\nwidth: 3rem;"},{"type":"input","ref":"limits.domax","css":"flex: 0 0 auto;\nheight: 1.5625rem;\nwidth: 3rem;"},{"format":"ppm"}]},{"classes":"container","css":"justify-content: center;\nalign-items: center;\ngap: 0.5rem;\nflex-wrap: wrap;","layout":[{"format":"PH","__label":"text","css":"flex: 0 0 auto;\ncolor: #304fe8;\nwidth: 7rem;\nheight: 1.0625rem;"},{"type":"input","ref":"limits.phmin","css":"flex: 0 0 auto;\nheight: 1.5625rem;\nwidth: 3rem;"},{"type":"input","ref":"limits.phmax","css":"flex: 0 0 auto;\nheight: 1.5625rem;\nwidth: 3rem;"}]},{"classes":"container","css":"justify-content: center;\nalign-items: center;\ngap: 0.5rem;\nflex-wrap: wrap;","layout":[{"format":"Water Temperature","__label":"text","css":"flex: 0 0 auto;\ncolor: #304fe8;\nwidth: 8.75rem;\nheight: 1.0625rem;"},{"type":"input","ref":"limits.wtempmin","css":"flex: 0 0 auto;\nheight: 1.5625rem;\nwidth: 3rem;"},{"type":"input","ref":"limits.wtempmax","css":"flex: 0 0 auto;\nheight: 1.5625rem;\nwidth: 3rem;"},{"format":"˚C","css":"height: 1.0625rem;"}]},{"classes":"container","css":"justify-content: center;\nalign-items: center;\ngap: 0.5rem;\nflex-wrap: wrap;","layout":[{"format":"Ambient Temperature","__label":"text","css":"flex: 0 0 auto;\ncolor: #304fe8;\nwidth: 8.75rem;\nheight: 1.0625rem;"},{"type":"input","ref":"limits.atempmin","css":"flex: 0 0 auto;\nheight: 1.5625rem;\nwidth: 3rem;"},{"type":"input","ref":"limits.atempmax","css":"flex: 0 0 auto;\nheight: 1.5625rem;\nwidth: 3rem;"},{"format":"˚C","css":"height: 1.0625rem;"}]},{"classes":"container","css":"justify-content: center;\nalign-items: center;\ngap: 0.5rem;\nflex-wrap: wrap;","layout":[{"format":"Humidity","__label":"text","css":"flex: 0 0 auto;\ncolor: #304fe8;\nwidth: 9rem;\nheight: 1.0625rem;"},{"type":"input","ref":"limits.phmin","css":"flex: 0 0 auto;\nheight: 1.5625rem;\nwidth: 3rem;"},{"type":"input","ref":"limits.hummax","css":"flex: 0 0 auto;\nheight: 1.5625rem;\nwidth: 3rem;"},{"format":"%","css":"flex: 0 0 auto;\nwidth: 1.0458984375rem;\nheight: 1.0625rem;"}]}]}]},{"type":"savebutton","title":"save all","icon":"save","ref":"limits","css":"font-size: 1.5rem;"}],"css":"flex: 0 0 auto;\njustify-content: center;\nheight: 71.314453125rem;\nwidth: 22rem;"},{"title":"Schedule Profiles","icon":"edit","css":"padding: 0.75rem;\ngap: 0.5rem;\nmin-height: 2rem;\ndisplay: flex;\nflex-direction: column;\nflex-grow: 1;","layout":[{"classes":"container","css":"gap: 0.5rem;\nflex-wrap: wrap;","layout":[{"classes":"panel","css":"flex: 0 0 auto;\nflex-basis: 0 0 auto;\nwidth: 35.75rem;","layout":[{"classes":"container","css":"font-size: 2rem;\nbackground: #86a3ac;\ngap: 0.5rem;","layout":[{"css":"color: #fefbfb;\nwhite-space: nowrap;\ntext-overflow: ellipsis;\nfont-weight: 700;","format":"Schedule Profiles"},{"format":"${profile.msg}","classes":"\n","css":"flex: 0 0 auto;\ncolor: #fdfcfc;\nheight: 2.375rem;\nwidth: 17.25rem;\ntext-align: center;"}]},{"css":"display:flex; align-items:center; justify-content:space-between; gap: 1rem;","layout":[{"type":"input","ref":"profile.schedule","css":"flex: 0 0 auto;\nwidth: 33.75rem;\nheight: 2rem;\noverflow-y: auto;\nwhite-space: pre-wrap;\nfont-family: Arial, sans-serif;\nbackground: white;\nresize: none;\nline-height: 1.4;\noutline: none;"}]},{"format":"${profile.schedule}"},{"css":"margin-top: 0.25rem;\njustify-content: center;\ndisplay: flex;\nalign-items: center;\ngap: 1rem;","layout":[{"type":"savebutton","ref":"profile","title":"save","icon":"save","css":"margin-left: 6.5rem;\nfont-size: 1.5rem;"},{"type":"action","title":"reboot","icon":"refresh","ref":"reboot","css":"flex: 0 0 auto;\nfont-size: 1.5rem;\nheight: 2.314453125rem;\nwidth: 8.25rem;","disabled":"${settings.disable_val>0}"}]}]}],"ref":""}]},{"title":"Production","icon":"forwards","classes":"page","layout":[{"classes":"container","css":"flex: 0 0 auto;\nheight: 14.8515625rem;\nwidth: 27.25rem;\ngap: 0.5rem;\nflex-wrap: wrap;","layout":[{"classes":"panel","css":"flex: 0 0 auto;\nheight: 10.546875rem;\nbackground: #ffffff;\nflex-basis: 0 0 auto;\nwidth: 27.546875rem;","layout":[{"classes":"container","css":"height: 3.25rem;\ncolor: #fefbfb;\nbackground: #86a3ac;\njustify-content: center;\ngap: 0.5rem;","layout":[{"classes":"title","format":"Production","css":"font-size: 2rem;\nheight: 2.3876953125rem;"}]},{"classes":"labeled","layout":[{"classes":"label","format":"Profile","css":"flex: 0 0 auto;\nheight: 1.0625rem;\nwidth: 2.75rem;"},{"type":"input","ref":"Prod.profile","css":"flex: 0 0 auto;\nwidth: 4rem;\ntext-align: center;","input":"number","autosave":false},{"format":"Cycle","css":"flex: 0 0 auto;\nheight: 1.0625rem;\nwidth: 2.2490234375rem;"},{"type":"input","ref":"Prod.cycle","css":"flex: 0 0 auto;\nheight: 1.5625rem;\nwidth: 4rem;","input":"number"},{"format":"Day","css":"flex: 0 0 auto;\nheight: 1.0625rem;\nwidth: 1.548828125rem;"},{"type":"input","ref":"Prod.day","css":"flex: 0 0 auto;\nheight: 1.5625rem;\nwidth: 4rem;","input":"number"}],"css":"justify-content: center;"},{"classes":"container","css":"color: #86a3ac;\njustify-content: center;\nbackground: #86a3ac;\ngap: 0.5rem;\nflex-wrap: wrap;","layout":[{"type":"dropdown","ref":"Prod.cmd","options":"Start,Stop,Harvest,Park","css":"font-weight: 1000;"}]},{"classes":"labeled","layout":[{"type":"savebutton","title":"Save & Reboot","icon":"save","ref":"Prod","css":"flex: 0 0 auto;\nwidth: 25.921875rem;\nfont-size: 1.25rem;\nheight: 2.001953125rem;","disabled":"${settings.disable_val>0}"}]}]}]}],"css":"flex: 0 0 auto;\nwidth: 15.75rem;\nheight: 1.6416015625rem;"}],"heartbeat":0,"login":{"title":"login","icon":"user","level":0,"classes":"page","layout":[]}},"http":{"http":true,"https":false,"ui":true,"login":false,"ca":""},"mqtt":{"enable":false,"url":"mqtt://broker.hivemq.com:1883","ca":"","rx":"{device_id}/rx","tx":"{device_id}/tx"},"dns":{"type":"default","url":"udp://8.8.8.8:53","captive":false,"mdns":false,"localname":"mongoose"},"sntp":{"enable":false,"type":0,"url":"udp://time.google.com:123","interval":3600},"modbus":{"enable":false,"port":502},"build":{"mode":"new","board":"esp32","ide":"ESP-IDF","rtos":"baremetal"},"websocket":{"enable":false}}